Workbook

Sheet Read me
A1: Corner Lands rework: steps 0 and 1
A3: What this is | B3: A draft of the ground rules (step 0) and the basic line of every industry with its gates (step 1). Nothing here is built yet: edit freely, and the game will be built from what you settle on.
A4: How to edit | B4: Yellow cells are yours: your call on each rule, and your notes. Blue numbers are levers (knowledge costs, rates, counts, months): change them and the budget checks update.
A5: Tabs | B5: 0 Ground rules: what each currency is for and the limits every design follows. 0 Stages: the five ranks, how long each should last and what the player does in it. 0 Knowledge: where knowledge comes from at each stage, and the budget it gives. 1 Basic lines: every industry's default chain, each unlock with its rank, knowledge cost and condition. 1 Budget check: do each stage's unlocks fit its knowledge budget? 1 Goods coverage: every good, where it comes from after step 1, and what uses it today. Questions: decisions I need from you before building.
A6: Gate notation | B6: Rank = the town size it waits for (a floor, never the whole gate). Knowledge = what it costs to learn, spent like prestige. Condition = learn by doing: produced so many of a good in total, or a building owned.
A7: Not in this pass | B7: Civic buildings, housing needs (step 2); mixed and late goods such as stained glass, fine clothes, books, arms, wine and jewellery (step 3); extensions, upgrades and choices (step 4); manor, great works, charters (steps 5 and 6). They appear here only where a basic line leads into them.

Sheet Decisions
A1: Settled, and carried into later steps
A2: Your answers to my doubts after the first pass, and what each later step must pick up.
A4: # | B4: Doubt | C4: Settled | D4: Picked up in
A5: 1 | B5: Rank or knowledge? | C5: Either, never both: a few gateway buildings by rank, the rest by knowledge with no rank floor. A town that rushes the glassworks imports sand until it is a Town. | D5: Done (G1, G6)
A6: 2 | B6: Knowledge pace vs essentials | C6: Timber House no longer needs drink: it needs a wooden church, water and two food groups, so its knowledge essentials fit the Hamlet's year. Townhouse checked again once its needs are set. | D6: Step 2
A7: 3 | B7: Fuel | C7: Per batch; firewood 1 unit, charcoal 2; glassworks needs charcoal; homes burn firewood only. | D7: Done (G18)
A8: 4 | B8: The Cooper's condition | C8: Kept as the one exception. | D8: Done (G7)
A9: 5 | B9: Taxes and early coins | C9: Building a manor becomes pressing. The settlers bring tools for two years of a regular set of simple buildings (about 11 tools at the new upkeep rates: see 2 Upkeep). | D9: Step 2 (manor, tax offices)
A10: 6 | B10: First crop | C10: Vegetables (turnips, cabbages, beans) instead of potatoes; the existing good. | D10: Done
A11: 7 | B11: Herbs as weak medicine | C11: Yes: herbs run out three times as fast as medicine. Fine-tune later. | D11: Step 2
A12: 8 | B12: Beekeeper and hives | C12: Both: the beekeeper produces, homemade hives are a small passive. | D12: Done
A13: 9 | B13: Timber House needs | C13: Neither clothes nor drink. Cider no longer marked. | D13: Step 2
A14: 10 | B14: Paper | C14: A Paper Mill (flax, by water) for everyone; the Scriptorium makes books only. Administrative buildings should have options to be fed; failing that, they work worse without paper. | D14: Step 2
A15: 11 | B15: Schools | C15: A public school or a Sunday school (church extension). If both: the public school gives a fixed trickle and slows all work 1-2%; the Sunday school slows work 2-3% but gives knowledge in proportion to the homes it serves. | D15: Steps 2 and 4
A17: Ideas for feeding administrative buildings (to discuss in step 2)
B18: Tally sticks | C18: Notched sticks from the carpenter: cheap and early, but an office on tally sticks handles fewer households.
B19: Wax tablets | C19: From beekeepers' wax: reusable, so used slowly; ties the beekeeper into the town's running.
B20: Parchment | C20: From hides at a parchmenter: dear, but it gives hides a third use.
B21: Paper | C21: From the Paper Mill: the best, full efficiency.
A23: Step 2, round 2
B24: Scale | C24: Only timber and coin costs come down; production, food, storage, taxes and prices stay; rebalance at the end (G19). Costs stay flat across tiers, finer materials instead (G21). Simple buildings wear at most a tool a year (2 Upkeep).
B25: Fine pottery | C25: A luxury only.
B26: Luxuries | C26: Jewellery, fine clothes, glass, wine, fine pottery. Books and mead are not luxuries.
B27: Garments | C27: Clothes or boots for the Townhouse; both for the Merchant's House.
B28: Bathhouse | C28: Opens at Borough.
B29: Builder's Yard | C29: Waits for a Draught Stable (exception to G7).
B30: Market, Alehouse, Courthouse, church, armoury, potter | C30: As I read them: by crew; policing past Borough; one church per town; armoury to the manor (step 5); potter uses dye.
A32: Costs edit and step 3
B33: Production speed | C33: Most non-food goods slow down to match the cheaper buildings; provisionally a third of today's speed (your costs are a third of today's on the median). To watch: your new upkeep is higher than today's for most workshops, so tools could get scarce. Settled in step 8.
B34: Home sizes | C34: Residents no longer grow much with the home's level: Townhouse, Merchant's and Patrician houses all hold 9, so a big town has more homes, and markets and alehouses serve by crew.
B35: Manor grounds | C35: Every manor building must touch the manor or a manor decoration that touches it; the manor's grounds blend into one dirt shape (art). Step 5.
B36: Watch towers | C36: At most 2 for each rank above Village. Step 5.
B37: Roads and orchards | C37: Stone road 2 stone a tile, cobbles 2 dressed stone a tile, orchards keep 2 coins a tile.
B38: Step 3 | C38: All agreed: Embroiderer and Glazier, parchment, mead for all, watch wears clothes and boots, medicine for sickness, jeweller sets silver with glass, books bought or charter. Silver to watch closely. Monasteries only consume books (no copying extension).
A40: Step 4
B41: Extensions | C41: A workplace may have several different extensions, each built once; they add an ability and may add a flat bonus.
B42: Upgrades | C42: Usually places and another bonus together; chains are possible (the stores already have one: loft, then improved).
B43: Learning by doing | C43: Required for upgrades and extensions, optional for variants and choices.
B44: Your additions | C44: Large woodcutter's lodge, ox tool-shed, water sawmill as a building, roads behind knowledge, cattle breeds as a choice, animal sheds, pears and strawberries, fish pond, trade choices, goods cart, trade centre, huge ships, expanded draught stable, mounted guard, improved stores, ox-carts.
B45: Dropped | C45: Roofs and heraldic banners are no longer in the table (5 Questions asks whether on purpose).
A1002: Step 5
B1003: Palace | C1003: The fourth manor level is a Palace (Borough).
B1004: Atelier | C1004: The Patrons' Atelier replaces the dovecote and makes the works of art by chance; the old commissions are gone.
B1005: Barracks | C1005: Replaces the gatehouse; raises the retinue and helps the courthouse.
B1006: Titles | C1006: Baron, Earl, Marquess, Duke: bought with prestige.
B1007: Great Works | C1007: Bell tower: all work 2% faster. Cathedral 3 prestige; university 8 knowledge. New: the Royal Road.
B1008: Step 4 leftovers | C1008: Pears to step 4, strawberries a new good, Frisian and Highland cattle, the trade upgrades stack in two steps, huge ships per year, banners kept.
B1009: Late knowledge | C1009: Inflate the late, non-essential prices by a lot (lever in 4 Depth, now x4); a player should need many years to learn everything.
A1011: Step 6
B1012: Paths | C1012: Eight paths: Artisans' Guilds added; Ironmongers replace Armourers; Heavy Plough empowers the iron plough. Every path keeps a drawback; choices are never re-picked.
B1013: Your edits | C1013: Deep Veins reveals 2-4 silver veins (Silver Mine); trade prices from guilds 1.25-1.5 rather than double; Woodland Lore half again; Druids let homes level with one need unmet; Royal Hunt adds two deer herds.
B1014: Prices | C1014: Rise exponentially so a regular player completes about two full paths (6 charters); see 6 Charter costs. Rechecked in step 8.
A1016: Step 7
B1017: Learning panel | C1017: A wooden board of scout patches per craft, related patches grouped (no columns). Civic, learning, trade and roads share a tab; thin tabs may merge. Nothing hidden: locked until learnable. No suggested strip: Fingamoboblius explains. Old saves kept if easy.
B1018: Late knowledge | C1018: No City projects. Knowledge gain and prices rebalanced so a player completes every unlock a few years after reaching City (your first idea: gains divided by 8 plus small grants on reaching ranks); I tune it against bot playthroughs, keeping each home level's essentials affordable in time (G9).
B1019: Silver, deer | C1019: Silver veins from Deep Veins only. Deer herds are simply more game for hunters.
B1020: Build | C1020: Go ahead: build, balance, test, design everything new on a branch; merge to main when happy. Then review drawings, remake the tutorial, and add a small symbol on every panel that calls Fingamoboblius to explain it.

Sheet 0 Ground rules
A1: Step 0: ground rules
A2: Every later step is checked against these. Mark each one Agree / Change / Drop in the yellow column.
A4: ID | B4: Area | C4: Rule | D4: Why | E4: Your call | F4: Your notes | G4: Status
A5: Currencies
A6: G1 | B6: Town rank | C6: Town rank decides how big the town may grow: house levels, manor levels, Great Works and decorations. A few gateway buildings unlock by rank alone (Farmstead: Hamlet; Clay Pit and Bloomery: Village; Sand Pit: Town). | D6: Rank already drives houses and the manor; keeping it to "size" stops it competing with knowledge. | E6: Change | F6: Basic industries buildings will be unlocked by rank alone | G6: Revised to your note
A7: G2 | B7: Knowledge | C7: Knowledge decides what your people know how to build: every building outside the starting set, extra recipes, crops, animals, workplace extensions and upgrades. It is spent, like prestige. | D7: Spending makes each unlock a choice; a threshold would just open everything in order. | E7: Agree | G7: As agreed
A8: G3 | B8: Prestige | C8: Prestige is the lord's: charters, titles, feasts and fairs, works of art, the retinue. It never unlocks ordinary industry. | D8: Players always know which currency they need. | E8: Agree | G8: As agreed
A9: G4 | B9: Charters | C9: Charters are the town's specialisation: exclusive choices, guild buildings and strong bonuses. A charter building may offer another way to meet a need, but never the only way. | D9: No town is locked out of a house level by the path it chose. | E9: Agree | G9: As agreed
A10: G5 | B10: Coins | C10: Coins run the economy and are never a gate. Taxes are collected only once there is a manor; the manor taxes up to the first 45 villagers (a Town's worth), and beyond that tax offices must be built (step 2). | E10: Change | F10: Let's add taxation system. Taxas can only be collected once a manor is built, the mannor can collect taxes from up to the population necessary to reach town, then tax offices must be built | G10: Revised to your note
A11: Gates
A12: G6 | B12: Shape | C12: Every unlock has either a rank or a knowledge cost, never both. Knowledge unlocks have no rank floor: their price is what makes them feasible or not. | D12: One readable line per unlock: "Town · 8 knowledge · after 40 ore". | E12: Change | F12: Let's not use rank for knowledge unlocks, the knowloedge price will somewhat define what is feasible for unlocking. | G12: Revised to your note
A13: G7 | B13: Conditions | C13: Conditions (learning by doing) are only for choices, extensions, some decorations and special buildings, never for production buildings. Exception: the Cooper waits for a trading post, dock or winery, since crates are useless without trade. | D13: Gives the "you learn by doing" feel without a second experience currency. | E13: Change | F13: We will drop conditions like this from all production buildings and leave only for choices, extensions and later some decorations and special buildings | G13: Revised to your note
A14: G8 | B14: Cost bands | C14: Knowledge prices: the basic building that reaches the end of a production line is cheap; extensions, choices and more efficient buildings cost in proportion to their bonus. | D14: Basic industry should not be hard to unlock; knowledge becomes the real constraint from Town on. | E14: Change | F14: I agree with the why. Basic building to get to the end of production line will be cheap, extensions, choices and more efficient buildings are more expensive proportionally to the bonus | G14: Revised to your note
A15: G9 | B15: Budgets | C15: What the next house level needs must fit inside a stage's basic budget with room to spare. Optional lines may add up to more than the budget, so the player chooses what to learn first. | D15: Nobody stalls on a house level; there is still a choice. | E15: Agree | G15: As agreed
A16: G10 | B16: Starting set | C16: Free from the start: Cottage, Woodcutter (timber and firewood), Sawmill, Quarry, Forager (berries), Hunter, Fisher, Storehouse, Granary, Well, Market, and the vegetable patch and hen coop in backyards. Mushrooms stop being a good (they stay on the map). | D16: Enough to survive the first winter; everything else is learned. | E16: Change | F16: Maybe not fit here, but since we will already have lot's of good types, we don't need mushrooms anymore and they were hard to spot anyway. Let's keep the visual mushrooms but they don't count towards food distribution rules nor are good anymore | G16: Revised to your note
A17: G11 | B17: Data | C17: Every gate lives in one table (this workbook's 1 Basic lines, later more) that the game reads. | D17: You can rebalance in the sheet. | E17: Agree | G17: As agreed
A18: Goods and buildings
A19: G12 | B19: Build costs | C19: At most 4 materials plus coins in any build or upgrade cost. | D19: New materials replace old ones rather than lengthen lists. | E19: Agree | G19: As agreed
A20: G13 | B20: Recipes | C20: At most 3 inputs per recipe. | E20: Agree | G20: As agreed
A21: G14 | B21: Every good | C21: Every good has a source by the stage it is needed (made, or bought as a stopgap) and a use. Foods count as used by being eaten. Intermediate goods (flour, hides, woad) need only the chain they feed. Finished goods need two uses: a recipe, a build cost, upkeep, a home need, a luxury or tavern drink; a luxury may count export as one. | D21: No dead ends, and no goods that only exist to be sold (oats today). | E21: Agree | G21: As agreed
A22: G15 | B22: Upkeep | C22: Simple buildings wear tools or wood parts at low rates from the start; if the town is slow to make them, it imports them. The settlers bring enough tools for two years of a regular set of simple buildings. | D22: Today woodcutters, quarries and farms wear tools that cannot be made before a Town. | E22: Change | F22: Simple buildings consume at lower rates, yes, but they can consume tools or parts, if the player is too slow in developing the industry, they must be imported. | G22: Revised to your note
A23: G16 | B23: One craft | C23: A building does one craft. Several recipes only where they share the workplace and skill (tailor: clothes and boots). Fine clothes get their own building. | D23: Keeps the build menu readable. | E23: Change | F23: Fine clothes will have their own building | G23: Revised to your note
A24: G17 | B24: Pace | C24: Each rank opens at most three new lines (a line = a new raw good and what it becomes). | D24: One thing to learn at a time. | E24: Agree | G24: As agreed
A25: G18 | B25: Fuel | C25: Workshops with a fire burn fuel with each batch, like an input, so an idle workshop burns nothing. One firewood is one unit of fuel and one charcoal two. Fuel burners: bakery, brewhouse, kiln, potter, lime kiln, bloomery, blacksmith, dyer. The glassworks needs charcoal itself, for the heat. Homes heat with firewood only. | D25: Your answer to doubt 3: always fuel, charcoal just more efficient. | E25: Agree | G25: New, from your answers
A26: G19 | B26: Scale | C26: Construction costs are as in 2 Costs (about a third of today's material on the median). To match, most non-food goods are made more slowly (provisionally a third of today's speed). Food production, storage, taxes and prices wait for the rebalance (step 8). | D26: Your answer: reduce the production speed of most goods; food waits for step 8. | G26: Revised to your note
A27: G20 | B27: Crew | C27: Everything a building does scales with how many of its places are filled: output, upkeep, and also services (how many homes an alehouse or market serves, how much a trading post moves, how fast haulers fetch, how much a builder's yard speeds, how much a monastery or university teaches). | D27: Today output and upkeep scale with the crew, but most services work at full strength with a single worker. | G27: New, from your note
A28: G21 | B28: Costs | C28: A building costs roughly the same number of units whatever its tier (about 3-12; Great Works more). Higher tiers ask for finer materials, or more of a simpler one, not ever bigger piles. | D28: Your balance reference. | E28: Agree | G28: New, from your note

Sheet 0 Knowledge
A1: Step 0: where knowledge comes from
A2: Typical count = how many a town has on average during that stage (blue, edit them). The totals feed 0 Stages.
A4: Source | B4: From rank | C4: Knowledge a month each | D4: Hamlet (count) | E4: Village (count) | F4: Town (count) | G4: Borough (count) | H4: City (count) | I4: Change from today
A5: Elders' lore (camp, then manor hall) | B5: Hamlet | C5: 0.1 | D5: 1 | E5: 1 | F5: 1 | G5: 1 | H5: 1 | I5: New: a trickle from the first day, so the Hamlet can learn.
A6: Wooden church | B6: Village | C6: 0.25 | D6: 0 | E6: 1 | F6: 0 | G6: 0 | H6: 0 | I6: Moves from Town to Village (step 2 to confirm).
A7: Stone Church | B7: Town | C7: 1 | D7: 0 | E7: 0 | F7: 1 | G7: 1 | H7: 2
A8: Timber House (lived in) | B8: Village | C8: 0.05 | D8: 0 | E8: 10 | F8: 12 | G8: 15 | H8: 20 | I8: New: a little learning in every Timber House.
A9: Townhouse (lived in) | B9: Town | C9: 0.1 | D9: 0 | E9: 0 | F9: 6 | G9: 15 | H9: 20
A10: Merchant's House (lived in) | B10: Borough | C10: 0.25 | D10: 0 | E10: 0 | F10: 0 | G10: 6 | H10: 20
A11: Monastery (with its book) | B11: Town | C11: 3 | D11: 0 | E11: 0 | F11: 0.5 | G11: 1 | H11: 1
A12: Scriptorium at work (charter) | B12: Town | C12: 1 | D12: 0 | E12: 0 | F12: 0 | G12: 0.5 | H12: 1
A13: University (with its books) | B13: Borough | C13: 10 | D13: 0 | E13: 0 | F13: 0 | G13: 0.3 | H13: 1
A14: Public school (or a Sunday school extension) | B14: Town | C14: 0.25 | D14: 0 | E14: 0 | F14: 1 | G14: 1 | H14: 1 | I14: New: slightly decrease efficiency (1 to 2% maybe)
A15: Cathedral | B15: Borough | C15: 3 | D15: 0 | E15: 0 | F15: 0 | G15: 0.2 | H15: 1
A16: Knowledge a month (average in stage) | D16: =SUMPRODUCT($C$5:$C$15,D5:D15) | E16: =SUMPRODUCT($C$5:$C$15,E5:E15) | F16: =SUMPRODUCT($C$5:$C$15,F5:F15) | G16: =SUMPRODUCT($C$5:$C$15,G5:G15) | H16: =SUMPRODUCT($C$5:$C$15,H5:H15)

Sheet 0 Stages
A1: Step 0: the stages of a game
A2: Months in stage and basic share are levers (blue). One month = 10 days.
A4: Rank | B4: Population from | C4: Months in stage | D4: Player focus | E4: Home level reached | F4: New lines (step 1) | G4: Knowledge a month | H4: Knowledge in stage | I4: Basic share | J4: Basic budget
A5: Hamlet | B5: 0 | C5: 12 | D5: Survive the first winter: food, firewood, shelter, somewhere to store it. Fell, quarry, gather, hunt, fish; the first fields. Trade possible. | E5: Cottage | F5: Timber (planks), first fields | G5: ='0 Knowledge'!D16 | H5: =C5*G5 | I5: 1 | J5: =H5*I5
A6: Village | B6: 20 | C6: 24 | D6: The first processing chains: bread, ale, cloth and clothes, tiles, animals, orchards. First trade. The church. Some second-tier chains | E6: Timber House | F6: Bread, ale and cider, cloth and leather, clay and tiles, herds, orchards | G6: ='0 Knowledge'!E16 | H6: =C6*G6 | I6: 0.7 | J6: =H6*I6
A7: Town | B7: 45 | C7: 36 | D7: First luxury, finish essential second-tier, begin specialization. The first charter. | E7: Townhouse | F7: Iron and tools, dressed stone and mortar, dyes, medicine, pottery | G7: ='0 Knowledge'!F16 | H7: =C7*G7 | I7: 0.5 | J7: =H7*I7
A8: Borough | B8: 90 | C8: 48 | D8: Luxuries and mixed goods: glass, fine clothes, books, arms. Great works begin. | E8: Merchant's House | F8: Glass | G8: ='0 Knowledge'!G16 | H8: =C8*G8 | I8: 0.15 | J8: =H8*I8
A9: City | B9: 150 | C9: 60 | D9: Great works, renown, refining the town: extensions, upgrades, choices. | E9: Merchant's House | F9: (extensions and choices, step 4) | G9: ='0 Knowledge'!H16 | H9: =C9*G9 | I9: 0 | J9: =H9*I9
A11: Basic share: how much of a stage's knowledge the basic lines may take; the rest is for mixed goods, extensions and choices (steps 3 and 4). Early stages are almost all basic industry.

Sheet 1 Basic lines
A1: Step 1: the basic line of every industry, and its gates
A2: Edit rank, knowledge and condition freely. "Essential" = needed for that stage's home level (see 1 Budget check).
A4: Line | B4: # | C4: Unlock | D4: Kind | E4: Makes | F4: From | G4: Rank | H4: Knowledge | I4: Condition (learn by doing) | J4: Upkeep (G15) | K4: Essential for | L4: Why this gate | M4: Change from today | N4: Your notes
A5: Timber | B5: 1 | C5: Woodcutter | D5: Building | E5: timber, firewood | G5: start | J5: Tools | L5: Start: the first thing every town needs. | M5: Wears wood parts from Village (today tools).
A6: Timber | B6: 2 | C6: Forester | D6: Building | E6: new trees | H6: 1 | J6: none | L6: Teaches replanting once the first woods thin. | M6: Was open from the start.
A7: Timber | B7: 3 | C7: Sawmill | D7: Building | E7: planks | F7: timber | G7: start | J7: Tools | K7: Timber House | L7: Timber Houses need planks the moment the town is a Village. | M7: Was Village.
A8: Timber | B8: 4 | C8: Carpenter | D8: Building | E8: wood parts | F8: planks | H8: 1 | J8: tools* | K8: Timber House | L8: Village buildings wear wood parts; mills are built with them. | M8: *wears tools only from Town on.
A9: Timber | B9: 5 | C9: Cooper | D9: Building | E9: crates | F9: planks, iron | H9: 3 | I9: a trading post built or dock or winery unlocked | J9: wood parts | L9: Crates matter once there is trade. | M9: Condition kept as an exception to G7: crates are useless without trade.
A10: Stone & earth | B10: 1 | C10: Quarry | D10: Building | E10: stone | G10: start | J10: Tools | L10: Start. | M10: Wears wood parts from Village (today tools).
A11: Stone & earth | B11: 2 | C11: Clay Pit | D11: Building | E11: clay | G11: Village | J11: wood parts | K11: Townhouse | L11: Needs a shore; the first earth line.
A12: Stone & earth | B12: 3 | C12: Kiln | D12: Building | E12: tiles | F12: clay + fuel | H12: 1 | J12: wood parts | K12: Townhouse | L12: Townhouses are roofed with tiles.
A13: Stone & earth | B13: 4 | C13: Stonemason | D13: Building | E13: dressed stone | F13: stone | H13: 2 | J13: tools | K13: Merchant's House | L13: Merchant's Houses, the stone manor and walls use dressed stone. | M13: Was Village.
A14: Stone & earth | B14: 5 | C14: Sand Pit | D14: Building | E14: sand | G14: Town | J14: tools | L14: Needs a shore; competes with the clay pit for it. | M14: Was Village.
A15: Stone & earth | B15: 6 | C15: Lime Kiln | D15: Building | E15: mortar | F15: stone, sand + fuel | H15: 2 | J15: tools | K15: Merchant's House | L15: Mortar joins dressed stone in the fine buildings (uses set in step 3). | M15: Was Village.
A16: Stone & earth | B16: 7 | C16: Potter | D16: Building | E16: fine pottery | F16: clay + fuel + dye | H16: 6 | J16: wood parts | K16: Merchant's House | L16: The finest homes want glazed pottery.
A17: Grain & bread | B17: 1 | C17: Farmstead + vegetables | D17: Building | E17: vegetables (turnips, cabbages, beans) | G17: Hamlet | J17: none | K17: Timber House | L17: The first food that is grown, not gathered. | M17: New easy first crop instead of wheat: eaten without milling, poor yield, feeds less. Reuses the vegetables good. Was Village with wheat. | N17: Potatos or generic vegetables can replace wheat as initial agriculture, since they need no forther work, giving unlucky players a way out (potatos must be inefficient to grow and to feed to counter the easy access)
A18: Grain & bread | B18: 2 | C18: Windmill + Wheat | D18: Building | E18: grain + flour | F18: grain | H18: 1 | J18: wood parts | M18: Wheat comes with the windmill.
A19: Grain & bread | B19: 3 | C19: Bakery | D19: Building | E19: bread | F19: flour + fuel | H19: 1 | J19: wood parts
A20: Grain & bread | B20: 4 | C20: Watermill | D20: Building | E20: flour | F20: grain | H20: 5 | J20: wood parts | L20: The bigger mill, for towns on a river.
A21: Grain & bread | B21: 5 | C21: Barley | D21: Crop | E21: barley | H21: 1 | K21: Townhouse
A22: Grain & bread | B22: 6 | C22: Brewhouse: ale | D22: Building | E22: ale | F22: barley + fuel | H22: 1 | J22: wood parts | K22: Townhouse | L22: Timber Houses want an alehouse with drink. | M22: Whichever drink is learned first unlocks the brewhouse with it; the other is a recipe. | N22: Whickever brewhouse picked first unlock the building and the obter unlock recipes
A23: Herds | B23: 1 | C23: Animal farm: sheep and pigs | D23: Building | E23: wool, pork, hides | H23: 2 | L23: Wool is the other way to cloth.
A24: Herds | B24: 2 | C24: Cattle | D24: Animal | E24: milk, meat, hides | H24: 2 | L24: The bigger, dearer beast. | M24: Was open with the animal farm.
A25: Herds | B25: 3 | C25: Dairy | D25: Building | E25: cheese | F25: milk | H25: 2 | J25: wood parts
A26: Orchards & hives | B26: 1 | C26: Orchard keeper: apples | D26: Building | E26: apples | H26: 1 | J26: wood parts
A27: Orchards & hives | B27: 2 | C27: Plums | D27: Crop | E27: plums | H27: 1 | L27: More fruit, more variety. | M27: Pears move to step 4 (a slow, rich variant).
A28: Orchards & hives | B28: 3 | C28: Brewhouse: cider | D28: Recipe | E28: cider | F28: apples + fuel | H28: 1 | L28: The other drink, for towns with orchards rather than barley.
A29: Orchards & hives | B29: 4 | C29: Beehives (backyard) | D29: Backyard | E29: honey | H29: 2 | L29: Bees follow the blossom.
A30: Orchards & hives | B30: 5 | C30: Beekeeper | D30: Building | E30: honey | H30: 2 | L30: The real honey producer; backyard hives stay as a small homemade extra. | M30: New building. | N30: New building
A31: Wild food & herbs | B31: 1 | C31: Forager, Hunter, Fisher | D31: Building | E31: berries, meat, fish | H31: 0 | J31: none | L31: Start. | M31: Mushrooms stop being a good; they stay on the map as decoration.
A32: Wild food & herbs | B32: 2 | C32: Forager: herbs | D32: Recipe | E32: herbs | H32: 1 | K32: Townhouse | L32: Herbs wait until the forager knows the woods. | M32: Was open from the start. Homes without medicine may use herbs instead, but herbs run out three times as fast. | N32: Herbs can serve as medicine, with dratically smaller efficiency
A33: Wild food & herbs | B33: 3 | C33: Apothecary | D33: Building | E33: medicine | F33: herbs | H33: 4 | J33: tools | K33: Townhouse | L33: Townhouses want medicine.
A34: Cloth & leather | B34: 1 | C34: Flax | D34: Crop | E34: flax | H34: 1 | K34: Townhouse | L34: Linen without sheep.
A35: Cloth & leather | B35: 2 | C35: Weaver | D35: Building | E35: cloth | F35: wool or flax | H35: 2 | J35: wood parts | K35: Townhouse
A36: Cloth & leather | B36: 3 | C36: Tailor: clothes | D36: Building | E36: clothes | F36: cloth | H36: 2 | J36: wood parts | K36: Townhouse | L36: Timber Houses need clothes.
A37: Cloth & leather | B37: 4 | C37: Tanner | D37: Building | E37: leather | F37: hides | H37: 2 | J37: wood parts | K37: Merchant's House
A38: Cloth & leather | B38: 5 | C38: Tailor: boots | D38: Recipe | E38: boots | F38: leather | H38: 3 | K38: Merchant's House | L38: Townhouses need boots. | M38: Was open with the tailor. Boots are now a Merchant's House need (step 2).
A39: Cloth & leather | B39: 6 | C39: Woad | D39: Crop | E39: woad | H39: 3 | L39: The dye line arrives with the Town.
A40: Cloth & leather | B40: 7 | C40: Dyer | D40: Building | E40: dyes | F40: woad or berries + fuel | H40: 5 | J40: wood parts | L40: Dyes feed fine clothes and stained glass (step 3). | M40: Berries are a second, food-hungry route to dyes. | N40: Adding berries give another route to dyies that consume a type of food that is limited
A41: Iron & tools | B41: 1 | C41: Bog Iron Pit | D41: Building | E41: ore | H41: 4 | J41: tools | L41: Needs bog ore on the map.
A42: Iron & tools | B42: 2 | C42: Charcoal Burner | D42: Building | E42: charcoal | F42: timber | H42: 3 | J42: tools | L42: The hot fuel for iron and glass.
A43: Iron & tools | B43: 3 | C43: Bloomery | D43: Building | E43: iron | F43: ore + fuel (charcoal best) | G43: Village | J43: tools | M43: Burns charcoal instead of firewood (gives charcoal its second use).
A44: Iron & tools | B44: 4 | C44: Blacksmith | D44: Building | E44: tools | F44: iron, timber + fuel | H44: 2 | J44: tools | L44: Town buildings wear tools; Townhouses are built with them. Until then, tools are bought. | M44: Not essential: tools can be imported until the town makes them (G15).
A45: Glass | B45: 1 | C45: Glassworks | D45: Building | E45: glass | F45: sand, charcoal | H45: 10 | J45: tools | K45: Merchant's House | L45: Glass is for the grandest buildings (uses set in step 3). | M45: Was Town. Still needs charcoal itself (G18). A town that rushes it imports sand until it is a Town. | N45: Glass can serve as luxury, besides contruction material
A46: Paper | B46: 1 | C46: Paper Mill | D46: Building | E46: paper | F46: flax | H46: 8 | J46: wood parts | K46: Administrative buildings | L46: Rag paper by water. Feeds the administrative buildings (step 2); they work worse without it. | M46: New. The charter Scriptorium becomes books only.
A48: Not here on purpose: Scriptorium, Winery and Jeweller stay charter buildings; Armoury, stained glass, fine clothes, books, wine, mead and jewellery are mixed or late goods (step 3); Silo, Trading Post, Dock, Alehouse, Builder's Yard, Draught Stable, Monastery and Church are civic (step 2).

Sheet 1 Budget check
A1: Steps 1-2: can each home level's essentials be learned by the time it opens?
A2: Counts the basic lines, civic buildings and step 3. Rank-gated, charter or free unlocks cost no knowledge (G6).
A4: Needed for | B4: Opens at | C4: Essential unlocks | D4: Knowledge for them | E4: Knowledge earned before it opens | F4: Fits? | G4: Spare
A5: Timber House | B5: Village | C5: =COUNTIF('1 Basic lines'!$K$5:$K$46,A5)+COUNTIF('2 Civic'!$I$5:$I$30,A5)+COUNTIF('3 Mixed & late'!$I$5:$I$12,A5) | D5: =SUMIF('1 Basic lines'!$K$5:$K$46,A5,'1 Basic lines'!$H$5:$H$46)+SUMIF('2 Civic'!$I$5:$I$30,A5,'2 Civic'!$E$5:$E$30)+SUMIF('3 Mixed & late'!$I$5:$I$12,A5,'3 Mixed & late'!$G$5:$G$12) | E5: ='0 Stages'!H5 | F5: =IF(D5<=E5,"Yes","No") | G5: =E5-D5
A6: Townhouse | B6: Town | C6: =COUNTIF('1 Basic lines'!$K$5:$K$46,A6)+COUNTIF('2 Civic'!$I$5:$I$30,A6)+COUNTIF('3 Mixed & late'!$I$5:$I$12,A6) | D6: =SUMIF('1 Basic lines'!$K$5:$K$46,A6,'1 Basic lines'!$H$5:$H$46)+SUMIF('2 Civic'!$I$5:$I$30,A6,'2 Civic'!$E$5:$E$30)+SUMIF('3 Mixed & late'!$I$5:$I$12,A6,'3 Mixed & late'!$G$5:$G$12) | E6: ='0 Stages'!H5+'0 Stages'!H6 | F6: =IF(D6<=E6,"Yes","No") | G6: =E6-D6
A7: Administrative buildings | B7: Town | C7: =COUNTIF('1 Basic lines'!$K$5:$K$46,A7)+COUNTIF('2 Civic'!$I$5:$I$30,A7)+COUNTIF('3 Mixed & late'!$I$5:$I$12,A7) | D7: =SUMIF('1 Basic lines'!$K$5:$K$46,A7,'1 Basic lines'!$H$5:$H$46)+SUMIF('2 Civic'!$I$5:$I$30,A7,'2 Civic'!$E$5:$E$30)+SUMIF('3 Mixed & late'!$I$5:$I$12,A7,'3 Mixed & late'!$G$5:$G$12) | E7: ='0 Stages'!H5+'0 Stages'!H6 | F7: =IF(D7<=E7,"Yes","No") | G7: =E7-D7
A8: Merchant's House | B8: Borough | C8: =COUNTIF('1 Basic lines'!$K$5:$K$46,A8)+COUNTIF('2 Civic'!$I$5:$I$30,A8)+COUNTIF('3 Mixed & late'!$I$5:$I$12,A8) | D8: =SUMIF('1 Basic lines'!$K$5:$K$46,A8,'1 Basic lines'!$H$5:$H$46)+SUMIF('2 Civic'!$I$5:$I$30,A8,'2 Civic'!$E$5:$E$30)+SUMIF('3 Mixed & late'!$I$5:$I$12,A8,'3 Mixed & late'!$G$5:$G$12) | E8: ='0 Stages'!H5+'0 Stages'!H6+'0 Stages'!H7 | F8: =IF(D8<=E8,"Yes","No") | G8: =E8-D8
A9: Patrician House | B9: City | C9: =COUNTIF('3 Mixed & late'!$I$5:$I$12,A9) | D9: =SUMIF('3 Mixed & late'!$I$5:$I$12,A9,'3 Mixed & late'!$G$5:$G$12) | E9: ='0 Stages'!H5+'0 Stages'!H6+'0 Stages'!H7+'0 Stages'!H8 | F9: =IF(D9<=E9,"Yes","No") | G9: =E9-D9
A10: Every unlock in steps 1-3 | B10: end of Town | C10: =COUNT('1 Basic lines'!$H$5:$H$46)+COUNT('2 Civic'!$E$5:$E$30)+COUNT('3 Mixed & late'!$G$5:$G$12) | D10: =SUM('1 Basic lines'!$H$5:$H$46)+SUM('2 Civic'!$E$5:$E$30)+SUM('3 Mixed & late'!$G$5:$G$12) | E10: ='0 Stages'!H5+'0 Stages'!H6+'0 Stages'!H7 | F10: =IF(D10<=E10,"Yes","No") | G10: =E10-D10
A12: Timber House: a wooden church (Village rank), a well (free) and two food groups, so only what column K marks costs knowledge.
A13: Townhouse: boots moved up and tools can be imported, so the iron line is no longer essential for it.

Sheet 1 Goods coverage
A1: Step 1: every good, its source after step 1, and its uses today
A2: Uses are read from the game as it is now. "Needs" flags goods with fewer than two uses (G14).
A4: Good | B4: Group | C4: Source after step 1 | D4: From rank | E4: Uses today | F4: Use count | G4: Status (G14) | H4: Your notes
A5: Timber | B5: materials | C5: Woodcutter | D5: start | E5: builds Burgage House; builds Woodcutter's Lodge; builds Forester's Hut; builds Stone Quarry; builds Bog Iron Pit; builds Clay Pit; builds Sand Pit; builds Forager's Hut; builds Hunting Camp; builds Fisher's Hut; builds Farmstead; builds Animal Farm; builds Orchard Keeper's Lodge; builds Windmill; builds Watermill; builds Bakery; builds Brewhouse; builds Dairy; builds Sawpit; Sawpit; builds Charcoal Burner; Charcoal Burner; builds Tannery; builds Weaver; builds Dyer's Workshop; builds Tailor & Cobbler; builds Carpenter's Workshop; builds Cooper's Workshop; builds Potter's Workshop; builds Stonemason's Yard; builds Lime Kiln; builds Tile Kiln; builds Bloomery; Blacksmith; builds Well; builds Storehouse; builds Granary; builds Silo; builds Trading Post; builds Dock; builds Draught Stable; builds Builder's Yard; builds Alehouse; builds Apothecary; builds Church; builds Flower Garden; builds Wayside Shrine; builds Public Garden; builds Maypole; builds Manor; builds Lord's Stable; upgrade to Timber House; Manor House | F5: 53 | G5: OK
A6: Firewood | B6: materials | C6: Woodcutter | D6: start | E6: Dyer's Workshop; Potter's Workshop; Lime Kiln; Tile Kiln; Bloomery | F6: 5 | G6: OK
A7: Planks | B7: materials | C7: Sawmill | D7: Hamlet | E7: builds Bog Iron Pit; builds Animal Farm; builds Orchard Keeper's Lodge; builds Brewhouse; builds Winery; builds Weaver; builds Dyer's Workshop; builds Tailor & Cobbler; builds Carpenter's Workshop; Carpenter's Workshop; builds Cooper's Workshop; Cooper's Workshop; builds Glassworks; builds Blacksmith; builds Armoury; Armoury; Armoury (bows); builds Jeweller's Shop; builds Trading Post; builds Dock; builds Draught Stable; builds Builder's Yard; builds Alehouse; builds Apothecary; builds Scriptorium; builds Church; builds Monastery; builds Manor; builds Lord's Stable; builds Watch Tower; builds Manor Garden; builds Bell Tower; builds Covered Market Hall; builds Cathedral; builds University; builds Guildhall; upgrade to Timber House; upgrade to Townhouse; upgrade to Merchant's House; Stone Manor | F7: 40 | G7: OK
A8: Wood Parts | B8: materials | C8: Carpenter | D8: Village | E8: builds Windmill; builds Watermill; builds Winery; upkeep | F8: 4 | G8: OK
A9: Stone | B9: materials | C9: Quarry | D9: start | E9: builds Watermill; builds Bakery; builds Winery; builds Potter's Workshop; builds Stonemason's Yard; Stonemason's Yard; builds Lime Kiln; Lime Kiln; builds Glassworks; builds Tile Kiln; builds Bloomery; builds Blacksmith; builds Armoury; builds Silo; builds Dock; builds Builder's Yard; builds Monastery; builds Wayside Shrine; builds Stone Fountain; builds Public Garden; builds Manor; builds Watch Tower; builds Town Wall; builds Manor Garden; builds Bell Tower; builds Cathedral; upgrade to Townhouse; Manor House; Stone Manor | F9: 29 | G9: OK
A10: Dressed Stone | B10: materials | C10: Stonemason | D10: Town | E10: builds Jeweller's Shop; builds Scriptorium; builds Town Wall; builds Lord's Statue; builds Bell Tower; builds Covered Market Hall; builds Cathedral; builds University; builds Guildhall; upgrade to Merchant's House; Stone Manor | F10: 11 | G10: OK
A11: Clay | B11: materials | C11: Clay Pit | D11: Village | E11: Potter's Workshop; Tile Kiln | F11: 2 | G11: OK
A12: Roof Tiles | B12: materials | C12: Kiln | D12: Village | E12: builds Monastery; builds Covered Market Hall; builds Cathedral; builds University; builds Guildhall; upgrade to Townhouse; upgrade to Merchant's House | F12: 7 | G12: OK
A13: Bog Iron | B13: materials | C13: Bog Iron Pit | D13: Town | E13: Bloomery | F13: 1 | G13: OK: feeds one chain
A14: Iron | B14: materials | C14: Bloomery | D14: Town | E14: Blacksmith; Armoury (armour) | F14: 2 | G14: OK
A15: Silver | B15: materials | C15: step 3: no source but a charter today | E15: Jeweller's Shop | F15: 1 | G15: OK: feeds one chain
A16: Crates | B16: materials | C16: Cooper | D16: Village | E16: Winery; trade carts | F16: 2 | G16: OK
A17: Sand | B17: materials | C17: Sand Pit | D17: Town | E17: Lime Kiln; Glassworks; Glassworks (glass) | F17: 3 | G17: OK
A18: Mortar | B18: materials | C18: Lime Kiln | D18: Town | F18: 0 | G18: No use yet: step 3
A19: Charcoal | B19: materials | C19: Charcoal Burner | D19: Town | E19: Glassworks; Glassworks (glass) | F19: 2 | G19: OK
A20: Glass | B20: materials | C20: Glassworks | D20: Borough | E20: Glassworks (stained glass) | F20: 1 | G20: OK: feeds one chain
A21: Stained Glass | B21: materials | C21: step 3: Glassworks recipe | E21: cathedral windows (commission) | F21: 1 | G21: OK: feeds one chain
A22: Bread | B22: food | C22: Bakery | D22: Village | E22: food | F22: 1 | G22: OK: food
A23: Meat | B23: food | C23: Forager, Hunter, Fisher | D23: start | E23: food | F23: 1 | G23: OK: food
A24: Pork | B24: food | C24: Animal farm: sheep and pigs | D24: Village | E24: food | F24: 1 | G24: OK: food
A25: Fish | B25: food | C25: Forager, Hunter, Fisher | D25: start | E25: food | F25: 1 | G25: OK: food
A26: Eggs | B26: food | C26: Hen coop (backyard) | D26: start | E26: food | F26: 1 | G26: OK: food
A27: Berries | B27: food | C27: Forager, Hunter, Fisher | D27: start | E27: food | F27: 1 | G27: OK: food
A28: Mushrooms | B28: food | C28: Forager, Hunter, Fisher | D28: start | E28: food | F28: 1 | G28: OK: food
A29: Vegetables | B29: food | C29: Vegetable patch (backyard) | D29: start | E29: food | F29: 1 | G29: OK: food
A30: Apples | B30: food | C30: Orchard keeper: apples | D30: Village | E30: Brewhouse (cider); food | F30: 2 | G30: OK: food
A31: Pears | B31: food | C31: Pears and plums | D31: Village | E31: food | F31: 1 | G31: OK: food
A32: Plums | B32: food | C32: Pears and plums | D32: Village | E32: food | F32: 1 | G32: OK: food
A33: Grapes | B33: food | C33: charter: vines | E33: Winery; food | F33: 2 | G33: OK: food
A34: Honey | B34: food | C34: Beehives (backyard) | D34: Village | E34: Brewhouse (mead); food | F34: 2 | G34: OK: food
A35: Milk | B35: food | C35: Cattle | D35: Village | E35: Dairy; food | F35: 2 | G35: OK: food
A36: Cheese | B36: food | C36: Dairy | D36: Village | E36: food | F36: 1 | G36: OK: food
A37: Wheat | B37: goods | C37: Farmstead + wheat fields | D37: Hamlet | E37: Windmill; Watermill | F37: 2 | G37: OK
A38: Barley | B38: goods | C38: Barley | D38: Village | E38: Brewhouse; Brewhouse (ale) | F38: 2 | G38: OK
A39: Oats | B39: goods | C39: none (unused) | F39: 0 | G39: Drop (folded into grain long ago)
A40: Flour | B40: goods | C40: Windmill | D40: Village | E40: Bakery | F40: 1 | G40: OK: feeds one chain
A41: Flax | B41: goods | C41: Flax | D41: Village | E41: Weaver (linen); Scriptorium; Scriptorium (paper) | F41: 3 | G41: OK
A42: Wool | B42: goods | C42: Animal farm: sheep and pigs | D42: Village | E42: Weaver; Weaver (woollen) | F42: 2 | G42: OK
A43: Hides | B43: goods | C43: Animal farm: sheep and pigs | D43: Village | E43: Tannery | F43: 1 | G43: OK: feeds one chain
A44: Leather | B44: goods | C44: Tanner | D44: Village | E44: Tailor & Cobbler (boots); Armoury (armour); Scriptorium (books) | F44: 3 | G44: OK
A45: Cloth | B45: goods | C45: Weaver | D45: Village | E45: Tailor & Cobbler; Tailor & Cobbler (clothes); Tailor & Cobbler (fine clothes) | F45: 3 | G45: OK
A46: Clothes | B46: goods | C46: Tailor: clothes | D46: Village | E46: home need | F46: 1 | G46: Finished good with one use: add one in step 3
A47: Boots | B47: goods | C47: Tailor: boots | D47: Town | E47: home need | F47: 1 | G47: Finished good with one use: add one in step 3
A48: Ale | B48: goods | C48: Brewhouse: ale | D48: Village | E48: tavern drink | F48: 1 | G48: Finished good with one use: add one in step 3
A49: Cider | B49: goods | C49: Brewhouse: cider | D49: Village | E49: tavern drink | F49: 1 | G49: Finished good with one use: add one in step 3
A50: Wine | B50: goods | C50: charter: Winery | E50: luxury; tavern drink | F50: 2 | G50: OK
A51: Mead | B51: goods | C51: charter: Meadmakers | E51: tavern drink | F51: 2 | G51: OK
A52: Herbs | B52: goods | C52: Forager: herbs | D52: Hamlet | E52: Apothecary | F52: 1 | G52: OK: feeds one chain
A53: Medicine | B53: goods | C53: Apothecary | D53: Town | E53: home need | F53: 1 | G53: Finished good with one use: add one in step 3
A54: Tools | B54: goods | C54: Blacksmith | D54: Town | E54: builds Lord's Statue; builds Cathedral; builds Guildhall; upgrade to Townhouse; upgrade to Merchant's House; upkeep | F54: 6 | G54: OK
A55: Paper | B55: goods | C55: charter: Scriptorium | E55: Scriptorium (books) | F55: 1 | G55: OK: feeds one chain
A56: Woad | B56: goods | C56: Woad | D56: Town | E56: Dyer's Workshop | F56: 1 | G56: OK: feeds one chain
A57: Dyes | B57: goods | C57: Dyer | D57: Town | E57: Tailor & Cobbler (fine clothes); Glassworks (stained glass) | F57: 2 | G57: OK
A58: Fine Clothes | B58: goods | C58: step 3: Tailor recipe | E58: luxury | F58: 1 | G58: Finished good with one use: add one in step 3
A59: Books | B59: goods | C59: charter: Scriptorium, or import | E59: builds University; | F59: 2 | G59: OK
A60: Jewellery | B60: goods | C60: step 3 (charter) | E60: luxury | F60: 1 | G60: Finished good with one use: add one in step 3
A61: Fine Pottery | B61: goods | C61: Potter | D61: Town | E61: luxury | F61: 1 | G61: Finished good with one use: add one in step 3
A62: Arms | B62: goods | C62: step 3: Armoury | E62: the lord's retinue | F62: 1 | G62: Finished good with one use: add one in step 3 | H62: Let's remove arms and make armoury a manor building that gives prestige and unlocks visuals (discuss later in manor)

Sheet 2 Housing
A1: Step 2: the housing ladder
A2: What each home level needs and what it gives back. Knowledge per home is linked from 0 Knowledge (green).
A4: Level | B4: Opens at | C4: Holds | D4: Tax × | E4: Upgrade cost | F4: Services nearby | G4: Goods it uses | H4: Food | I4: Knowledge a month | J4: Change from today | K4: Your notes
A5: Cottage | B5: Hamlet | C5: 5 | D5: 1 | E5: 3 timber (to build) | F5: — | G5: — | H5: Enough food; firewood in winter | I5: 0
A6: Timber House | B6: Village | C6: 7 | D6: 1.5 | E6: 3 planks, 2 timber | F6: A wooden church; a well, market stall | G6: — | H6: 2 food groups | I6: ='0 Knowledge'!C8 | J6: No longer needs a market, drink or clothes; now needs a church (your answer).
A7: Townhouse | B7: Town | C7: 9 | D7: 2 | E7: 5 planks, 4 tiles, 3 stone | F7: an alehouse or tavern with drink, a stone church | G7: Clothes or boots (either garment); medicine (herbs will do, used three times as fast) | H7: 3 food groups | I7: ='0 Knowledge'!C9 | J7: Drink and the market move here from the Timber House. Boots move up to the Merchant's House. The church need moves down to the Timber House.
A8: Merchant's House | B8: Borough | C8: 9 | D8: 3 | E8: 3 dressed stone, 5 tiles, 3 mortar, 1 glass, 5 coins | F8: A dressed stone church; a bathhouse (proposal) | G8: Clothes, boots, medicine; one luxury (jewellery, fine clothes, glass, wine or fine pottery) | H8: 4 food groups | I8: ='0 Knowledge'!C10 | J8: Mortar and glass replace planks and tools in the cost: their first real uses (G14). Glassware is a new luxury (your note). Fine pottery is now only a luxury; books and mead are no longer luxuries.
A9: Patrician House (proposal) | B9: City | C9: 9 | D9: 4 | E9: 5 dressed stone, 4 mortar, 1 stained glass, 25 coins | F9: As the Merchant's House, and a school (public or Sunday), a Great Work | G9: As the Merchant's House, plus fine clothes and two more luxury | H9: 4 food groups | I9: 0.75 | J9: New fifth level, so the City has a home to grow into. Your call. | K9: I like it, but I made it even more challeging
A11: Every level also needs everything the level below needs. Homes take goods from the market one at a time as they wear out (one every two months), as today.

Sheet 2 Civic
A1: Step 2: civic buildings, their gates and what they run on
A2: Gate follows G6: a rank or a knowledge cost (blue), never both. "Essential for" feeds 1 Budget check.
A4: Building | B4: Group | C4: What it does | D4: Gate | E4: Knowledge | F4: Cost (proposed) | G4: Workers | H4: Runs on | I4: Essential for | J4: Change from today | K4: Your notes
A5: Storage & logistics | F5: —
A6: Settlers' Camp | B6: Storage & logistics | C6: Shelter for eight and the settlers' store until houses and a storehouse stand. | D6: start | F6: — | G6: 0 | H6: —
A7: Storehouse | B7: Storage & logistics | C7: Stores 300 materials; its haulers fetch from workplaces. | D7: start | F7: 8 timber | G7: 2 | H7: —
A8: Granary | B8: Storage & logistics | C8: Stores 300 food. | D8: start | F8: 8 timber | G8: 2 | H8: —
A9: Silo | B9: Storage & logistics | C9: Keeps 1000 grain dry, so granaries stay free. | E9: 1 | F9: 5 timber, 4 stone | G9: 0 | H9: — | J9: Was Village rank.
A10: Draught Stable | B10: Storage & logistics | C10: Stalls for pack up to 3 horses and oxen. | E10: 2 | F10: 8 timber, 4 planks | G10: 0 | J10: Was open from the start. | K10: runs on nothing, not to mix with Noble stable
A11: Builder's Yard | B11: Storage & logistics | C11: With its ox, building sites nearby rise half as fast again. | E11: 3 | F11: 8 timber, 4 planks, 3 stone | G11: 2 | H11: wood parts | J11: Was open from the start. Waits for a Draught Stable: an exception to G7, like the Cooper.
A12: Water, food & drink
A13: Well | B13: Water, food & drink | C13: Water for homes nearby (Timber House need). | D13: start | F13: 3 stone | G13: 0 | H13: — | I13: Timber House
A14: Market | B14: Water, food & drink | C14: Stalls; each open stall serves ten households with their goods (Townhouse need). | D14: start | F14: free | G14: Depends on space for stalls (up to 1 workspace/stall for every 2 sqares) | H14: — | I14: Timber House | K14: Amount of houses served depend on number of workers
A15: Alehouse | B15: Water, food & drink | C15: Pours drink for homes nearby (Townhouse need). Enlarged into a Tavern once a Town: twice the reach. | D15: Town | F15: 4 timber, 1 planks | G15: 2 | H15: ale, cider, mead or wine | I15: Townhouse | J15: Was Village rank. Its drink is now a Townhouse need, not a Timber House one. | K15: Amount of houses served depend on number of workers
A16: Bathhouse (proposal) | B16: Water, food & drink | C16: Hot baths: a Merchant's House need, and cheer for homes nearby. | D16: Borough | F16: 5 stone, 3 planks, 2 tiles, 1 glass | G16: 2 | H16: fuel, a little | I16: Merchant's House | J16: New. Opens at Borough, with the Merchant's House that needs it. | K16: Amount of houses served depend on number of workers
A17: Trade
A18: Trading Post | B18: Trade | C18: Import and export orders; animals are bought here. | D18: start | F18: 8 timber | G18: 2 | H18: wood parts | J18: Was Village rank: the Hamlet can trade (0 Stages). | K18: No planks needed, no wood part upkeep
A19: Dock | B19: Trade | C19: Boats carry more and trade cheaper; on the water's edge. | E19: 4 | F19: 8 planks, 5 timber, 3 stone | G19: 3 | H19: wood parts | J19: Was Village rank.
A20: Faith & learning
A21: Wooden Church | B21: Faith & learning | C21: Happiness in a wide area; 0.25 knowledge a month (Timber House need). | D21: Village | F21: 10 timber, 5 planks, 10 coins | G21: 1 | H21: — | I21: Timber House | J21: Was Town. | K21: Let's limit 1/city of this or its upgrades
A22: Stone Church (rebuild) | B22: Faith & learning | C22: More happiness, prestige and knowledge (1 a month);Townhouse need. | D22: Town | F22: 8 stone, 4 tiles, 1 tools, 20 coins | G22: 1 | H22: — | I22: Townhouse | J22: Mortar and glass in place of planks and rough stone. | K22: intermediate church
A23: Dressed Stone Church (upgrade) | B23: Faith & learning | C23: More happiness, prestige and knowledge (2 a month);Merchan'ts House need. | D23: Borough | F23: 8 dressed stone, 3 mortar, 1 glass, 1 tools, 20 coins | I23: Merchant's House | K23: Now the final level
A24: Monastery | B24: Faith & learning | C24: Reads a book a month: 3 knowledge, a little prestige, +3 happiness town-wide. | E24: 10 | F24: 10 stone, 8 planks, 5 tiles, 3 mortar, 30 coins | G24: 2 | H24: 1 book a month | J24: Was Town rank; mortar added.
A25: Public School (proposal) | B25: Faith & learning | C25: 0.02 learning per house, efficiency malus of 3% | E25: 2 | F25: 5 planks, 3 tiles, 3 stone | G25: 1 | H25: — | J25: New. The Sunday school is its alternative, as a church extension (step 4). Let's keep both
A26: Scriptorium | B26: Faith & learning | C26: Copies books from paper and leather. Makes books and knowledge | D26: charter | F26: 4 dressed stone, 4 planks, 8 coins | G26: 3 | H26: paper, leather | J26: Books only: paper moves to the Paper Mill.
A27: Administration
A28: Manor (hall) | B28: Administration | C28: The lord's seat. Taxes start only once it stands, and it can tax up to 45 villagers. | D28: Hamlet | F28: 10 timber, 4 planks, 5 coins | G28: 0 | H28: — | J28: Taxes need it now; was optional. Reviewed with the manor (step 5).
A29: Courthouse | B29: Administration | D29: Borough | F29: 8 dressed stone, 4 mortar, 4 planks, 20 coins | K29: Starting at borough, increased population exponentially diminishes hapines without policiment
A30: Tax Office | B30: Administration | C30: Taxes 40 more villagers. Short of paper it manages only half; tally sticks (timber) can stand in at half. | D30: Town | E30: 4 | F30: 5 planks, 3 stone, 8 coins | G30: 2 | H30: 2 paper a month | I30: Administrative buildings | J30: New (your G5 note).
A31: Health
A32: Apothecary | B32: Health | C32: Herbs into medicine (in 1 Basic lines). | E32: 4 | F32: 4 timber, 3 planks | G32: 2 | H32: herbs + fuel | I32: Townhouse | J32: Listed here for completeness; its gate lives in 1 Basic lines.
A34: The Apothecary is counted in 1 Basic lines only (its row here is informational and is left out of the budget check).
A35: Taxes: before a manor, no taxes at all; a Hamlet lives on its stock and what it sells. Manor up to 45 villagers; each Tax Office 40 more.

Sheet 2 Costs
A1: Construction costs on the new scale
A2: Today's costs divided by about four (G19) and rounded, with the changes from steps 1-2. Blue numbers are yours to change; the checks on the right follow them.
A4: Building | B4: Group | C4: Cost today | D4: Timber | E4: Planks | F4: Wood parts | G4: Stone | H4: Dressed stone | I4: Tiles | J4: Mortar | K4: Glass | L4: Stained glass | M4: Tools | N4: Books | O4: Coins | P4: Materials | Q4: Units | R4: G12 (max 4) | S4: Notes | T4: Your notes
A5: Homes
A6: Cottage | B6: Homes | C6: 12 timber | D6: 4 | P6: =COUNT(D6:N6) | Q6: =SUM(D6:N6) | R6: =IF(P6<=4,"OK","Too many")
A7: Timber House (upgrade) | B7: Homes | C7: 12 planks, 6 timber | D7: 2 | E7: 4 | P7: =COUNT(D7:N7) | Q7: =SUM(D7:N7) | R7: =IF(P7<=4,"OK","Too many")
A8: Townhouse (upgrade) | B8: Homes | C8: 20 planks, 15 tiles, 10 stone | E8: 6 | G8: 4 | I8: 10 | P8: =COUNT(D8:N8) | Q8: =SUM(D8:N8) | R8: =IF(P8<=4,"OK","Too many") | S8: Tools dropped (your edit).
A9: Merchant's House (upgrade) | B9: Homes | C9: 10 dressed stone, 20 tiles, 10 mortar, 5 glass, 20 coins | H9: 6 | I9: 10 | J9: 4 | K9: 4 | O9: 20 | P9: =COUNT(D9:N9) | Q9: =SUM(D9:N9) | R9: =IF(P9<=4,"OK","Too many")
A10: Patrician House (upgrade) | B10: Homes | C10: 20 dressed stone, 15 mortar, 4 stained glass, 100 coins | H10: 6 | J10: 4 | K10: 10 | L10: 6 | O10: 100 | P10: =COUNT(D10:N10) | Q10: =SUM(D10:N10) | R10: =IF(P10<=4,"OK","Too many")
A11: Production: timber, stone & earth
A12: Woodcutter's Lodge | B12: Production | C12: 15 timber | D12: 5 | P12: =COUNT(D12:N12) | Q12: =SUM(D12:N12) | R12: =IF(P12<=4,"OK","Too many")
A13: Forester's Hut | B13: Production | C13: 8 timber | D13: 5 | P13: =COUNT(D13:N13) | Q13: =SUM(D13:N13) | R13: =IF(P13<=4,"OK","Too many")
A14: Sawpit | B14: Production | C14: 25 timber | D14: 4 | P14: =COUNT(D14:N14) | Q14: =SUM(D14:N14) | R14: =IF(P14<=4,"OK","Too many")
A15: Carpenter's Workshop | B15: Production | C15: 15 timber, 10 planks | D15: 4 | E15: 4 | P15: =COUNT(D15:N15) | Q15: =SUM(D15:N15) | R15: =IF(P15<=4,"OK","Too many")
A16: Cooper's Workshop | B16: Production | C16: 15 timber, 10 planks | D16: 4 | E16: 4 | P16: =COUNT(D16:N16) | Q16: =SUM(D16:N16) | R16: =IF(P16<=4,"OK","Too many")
A17: Stone Quarry | B17: Production | C17: 20 timber | D17: 5 | P17: =COUNT(D17:N17) | Q17: =SUM(D17:N17) | R17: =IF(P17<=4,"OK","Too many")
A18: Clay Pit | B18: Production | C18: 15 timber | D18: 4 | P18: =COUNT(D18:N18) | Q18: =SUM(D18:N18) | R18: =IF(P18<=4,"OK","Too many")
A19: Tile Kiln | B19: Production | C19: 15 timber, 8 stone | D19: 4 | G19: 4 | P19: =COUNT(D19:N19) | Q19: =SUM(D19:N19) | R19: =IF(P19<=4,"OK","Too many")
A20: Stonemason's Yard | B20: Production | C20: 20 timber, 4 stone | D20: 4 | G20: 2 | P20: =COUNT(D20:N20) | Q20: =SUM(D20:N20) | R20: =IF(P20<=4,"OK","Too many")
A21: Sand Pit | B21: Production | C21: 15 timber | D21: 4 | P21: =COUNT(D21:N21) | Q21: =SUM(D21:N21) | R21: =IF(P21<=4,"OK","Too many")
A22: Lime Kiln | B22: Production | C22: 20 stone, 10 timber | D22: 3 | G22: 6 | P22: =COUNT(D22:N22) | Q22: =SUM(D22:N22) | R22: =IF(P22<=4,"OK","Too many")
A23: Potter's Workshop | B23: Production | C23: 15 timber, 8 stone, 30 coins | D23: 4 | E23: 6 | G23: 2 | O23: 15 | P23: =COUNT(D23:N23) | Q23: =SUM(D23:N23) | R23: =IF(P23<=4,"OK","Too many")
A24: Production: food & farming
A25: Farmstead | B25: Production | C25: 25 timber | D25: 6 | P25: =COUNT(D25:N25) | Q25: =SUM(D25:N25) | R25: =IF(P25<=4,"OK","Too many")
A26: Windmill | B26: Production | C26: 25 timber, 4 wood parts | D26: 6 | F26: 4 | P26: =COUNT(D26:N26) | Q26: =SUM(D26:N26) | R26: =IF(P26<=4,"OK","Too many")
A27: Bakery | B27: Production | C27: 20 timber, 4 stone | D27: 4 | E27: 8 | G27: 2 | P27: =COUNT(D27:N27) | Q27: =SUM(D27:N27) | R27: =IF(P27<=4,"OK","Too many")
A28: Watermill | B28: Production | C28: 30 timber, 15 stone, 6 wood parts | D28: 14 | F28: 10 | G28: 4 | O28: 10 | P28: =COUNT(D28:N28) | Q28: =SUM(D28:N28) | R28: =IF(P28<=4,"OK","Too many")
A29: Brewhouse | B29: Production | C29: 20 timber, 10 planks | D29: 4 | E29: 8 | P29: =COUNT(D29:N29) | Q29: =SUM(D29:N29) | R29: =IF(P29<=4,"OK","Too many")
A30: Animal Farm | B30: Production | C30: 30 timber, 5 planks | D30: 6 | E30: 2 | P30: =COUNT(D30:N30) | Q30: =SUM(D30:N30) | R30: =IF(P30<=4,"OK","Too many")
A31: Dairy | B31: Production | C31: 20 timber | D31: 4 | E31: 6 | P31: =COUNT(D31:N31) | Q31: =SUM(D31:N31) | R31: =IF(P31<=4,"OK","Too many")
A32: Orchard Keeper's Lodge | B32: Production | C32: 20 timber, 5 planks | D32: 4 | E32: 2 | P32: =COUNT(D32:N32) | Q32: =SUM(D32:N32) | R32: =IF(P32<=4,"OK","Too many")
A33: Beekeeper | B33: Production | C33: free | D33: 2 | E33: 6 | O33: 15 | P33: =COUNT(D33:N33) | Q33: =SUM(D33:N33) | R33: =IF(P33<=4,"OK","Too many") | S33: New.
A34: Forager's Hut | B34: Production | C34: 10 timber | D34: 5 | P34: =COUNT(D34:N34) | Q34: =SUM(D34:N34) | R34: =IF(P34<=4,"OK","Too many")
A35: Hunting Camp | B35: Production | C35: 15 timber | D35: 5 | P35: =COUNT(D35:N35) | Q35: =SUM(D35:N35) | R35: =IF(P35<=4,"OK","Too many")
A36: Fisher's Hut | B36: Production | C36: 15 timber | D36: 5 | P36: =COUNT(D36:N36) | Q36: =SUM(D36:N36) | R36: =IF(P36<=4,"OK","Too many")
A37: Production: crafts & metal
A38: Apothecary | B38: Production | C38: 15 timber, 10 planks | E38: 8 | H38: 4 | I38: 8 | O38: 10 | P38: =COUNT(D38:N38) | Q38: =SUM(D38:N38) | R38: =IF(P38<=4,"OK","Too many")
A39: Weaver | B39: Production | C39: 20 timber, 5 planks | D39: 4 | E39: 8 | P39: =COUNT(D39:N39) | Q39: =SUM(D39:N39) | R39: =IF(P39<=4,"OK","Too many")
A40: Tailor & Cobbler | B40: Production | C40: 15 timber, 10 planks | D40: 4 | E40: 6 | G40: 2 | P40: =COUNT(D40:N40) | Q40: =SUM(D40:N40) | R40: =IF(P40<=4,"OK","Too many")
A41: Tannery | B41: Production | C41: 25 timber | D41: 4 | E41: 4 | P41: =COUNT(D41:N41) | Q41: =SUM(D41:N41) | R41: =IF(P41<=4,"OK","Too many")
A42: Dyer's Workshop | B42: Production | C42: 15 timber, 10 planks | D42: 4 | E42: 8 | G42: 4 | P42: =COUNT(D42:N42) | Q42: =SUM(D42:N42) | R42: =IF(P42<=4,"OK","Too many")
A43: Bog Iron Pit | B43: Production | C43: 30 timber, 10 planks | D43: 6 | E43: 4 | P43: =COUNT(D43:N43) | Q43: =SUM(D43:N43) | R43: =IF(P43<=4,"OK","Too many")
A44: Charcoal Burner | B44: Production | C44: 20 timber | D44: 4 | G44: 2 | P44: =COUNT(D44:N44) | Q44: =SUM(D44:N44) | R44: =IF(P44<=4,"OK","Too many")
A45: Bloomery | B45: Production | C45: 20 stone, 10 timber | D45: 2 | E45: 6 | G45: 6 | P45: =COUNT(D45:N45) | Q45: =SUM(D45:N45) | R45: =IF(P45<=4,"OK","Too many")
A46: Blacksmith | B46: Production | C46: 20 stone, 15 planks | E46: 8 | G46: 4 | P46: =COUNT(D46:N46) | Q46: =SUM(D46:N46) | R46: =IF(P46<=4,"OK","Too many")
A47: Glassworks | B47: Production | C47: 25 stone, 10 planks, 40 coins | E47: 8 | G47: 8 | M47: 2 | O47: 10 | P47: =COUNT(D47:N47) | Q47: =SUM(D47:N47) | R47: =IF(P47<=4,"OK","Too many")
A48: Paper Mill | B48: Production | C48: free | E48: 8 | F48: 4 | G48: 4 | P48: =COUNT(D48:N48) | Q48: =SUM(D48:N48) | R48: =IF(P48<=4,"OK","Too many") | S48: New: a wheel on the water.
A49: Winery (charter) | B49: Production | C49: 20 stone, 15 planks, 4 wood parts | E49: 10 | F49: 3 | G49: 5 | P49: =COUNT(D49:N49) | Q49: =SUM(D49:N49) | R49: =IF(P49<=4,"OK","Too many")
A50: Jeweller's Shop (charter) | B50: Production | C50: 15 dressed stone, 10 planks, 80 coins | H50: 8 | J50: 6 | K50: 4 | O50: 20 | P50: =COUNT(D50:N50) | Q50: =SUM(D50:N50) | R50: =IF(P50<=4,"OK","Too many")
A51: Scriptorium (charter) | B51: Production | C51: 15 dressed stone, 15 planks, 30 coins | E51: 8 | H51: 6 | J51: 4 | K51: 4 | O51: 15 | P51: =COUNT(D51:N51) | Q51: =SUM(D51:N51) | R51: =IF(P51<=4,"OK","Too many")
A52: Civic
A53: Storehouse | B53: Civic | C53: 30 timber | D53: 8 | P53: =COUNT(D53:N53) | Q53: =SUM(D53:N53) | R53: =IF(P53<=4,"OK","Too many")
A54: Granary | B54: Civic | C54: 30 timber | D54: 4 | G54: 6 | P54: =COUNT(D54:N54) | Q54: =SUM(D54:N54) | R54: =IF(P54<=4,"OK","Too many")
A55: Silo | B55: Civic | C55: 20 timber, 15 stone | D55: 6 | G55: 4 | P55: =COUNT(D55:N55) | Q55: =SUM(D55:N55) | R55: =IF(P55<=4,"OK","Too many")
A56: Draught Stable | B56: Civic | C56: 30 timber, 15 planks | D56: 6 | E56: 4 | P56: =COUNT(D56:N56) | Q56: =SUM(D56:N56) | R56: =IF(P56<=4,"OK","Too many")
A57: Builder's Yard | B57: Civic | C57: 30 timber, 15 planks, 10 stone | D57: 8 | E57: 4 | G57: 4 | P57: =COUNT(D57:N57) | Q57: =SUM(D57:N57) | R57: =IF(P57<=4,"OK","Too many")
A58: Well | B58: Civic | C58: 12 timber | G58: 6 | P58: =COUNT(D58:N58) | Q58: =SUM(D58:N58) | R58: =IF(P58<=4,"OK","Too many") | S58: Stone instead of timber (your edit).
A59: Market | B59: Civic | C59: free | P59: =COUNT(D59:N59) | Q59: =SUM(D59:N59) | R59: =IF(P59<=4,"OK","Too many") | S59: Free to lay out.
A60: Alehouse | B60: Civic | C60: 15 timber, 4 planks | D60: 4 | E60: 6 | G60: 6 | P60: =COUNT(D60:N60) | Q60: =SUM(D60:N60) | R60: =IF(P60<=4,"OK","Too many")
A61: Tavern (enlarge) | B61: Civic | C61: 20 timber, 15 planks, 10 stone | D61: 5 | E61: 4 | G61: 3 | P61: =COUNT(D61:N61) | Q61: =SUM(D61:N61) | R61: =IF(P61<=4,"OK","Too many")
A62: Bathhouse | B62: Civic | C62: free | E62: 4 | G62: 6 | I62: 4 | K62: 2 | P62: =COUNT(D62:N62) | Q62: =SUM(D62:N62) | R62: =IF(P62<=4,"OK","Too many") | S62: New.
A63: Trading Post | B63: Civic | C63: 30 timber, 10 planks | D63: 8 | P63: =COUNT(D63:N63) | Q63: =SUM(D63:N63) | R63: =IF(P63<=4,"OK","Too many") | S63: No planks (your edit).
A64: Dock | B64: Civic | C64: 30 planks, 20 timber, 10 stone | D64: 6 | E64: 10 | G64: 4 | P64: =COUNT(D64:N64) | Q64: =SUM(D64:N64) | R64: =IF(P64<=4,"OK","Too many")
A65: Wooden Church | B65: Civic | C65: 40 timber, 20 planks, 40 coins | D65: 10 | E65: 5 | P65: =COUNT(D65:N65) | Q65: =SUM(D65:N65) | R65: =IF(P65<=4,"OK","Too many")
A66: Stone Church (rebuild) | B66: Civic | C66: 30 stone, 15 tiles, 5 tools, 80 coins | G66: 8 | I66: 4 | M66: 1 | O66: 10 | P66: =COUNT(D66:N66) | Q66: =SUM(D66:N66) | R66: =IF(P66<=4,"OK","Too many")
A67: Dressed Stone Church (rebuild) | B67: Civic | C67: 30 dressed stone, 10 mortar, 4 glass, 5 tools, 80 coins | H67: 8 | J67: 4 | K67: 3 | M67: 1 | O67: 20 | P67: =COUNT(D67:N67) | Q67: =SUM(D67:N67) | R67: =IF(P67<=4,"OK","Too many")
A68: Monastery | B68: Civic | C68: 40 stone, 30 planks, 20 tiles, 10 mortar, 120 coins | E68: 8 | G68: 10 | I68: 10 | J68: 5 | O68: 30 | P68: =COUNT(D68:N68) | Q68: =SUM(D68:N68) | R68: =IF(P68<=4,"OK","Too many")
A69: Public School | B69: Civic | C69: 20 planks, 10 tiles, 10 stone | D69: 8 | E69: 10 | G69: 4 | I69: 6 | P69: =COUNT(D69:N69) | Q69: =SUM(D69:N69) | R69: =IF(P69<=4,"OK","Too many")
A70: Tax Office | B70: Civic | C70: 20 planks, 10 stone, 30 coins | E70: 10 | G70: 4 | O70: 10 | P70: =COUNT(D70:N70) | Q70: =SUM(D70:N70) | R70: =IF(P70<=4,"OK","Too many")
A71: Courthouse | B71: Civic | C71: free | E71: 6 | H71: 8 | J71: 4 | K71: 4 | O71: 20 | P71: =COUNT(D71:N71) | Q71: =SUM(D71:N71) | R71: =IF(P71<=4,"OK","Too many") | S71: New; your TBD.
A72: Manor
A73: Manor Hall | B73: Manor | C73: 60 timber, 20 planks, 20 stone, 60 coins | D73: 10 | E73: 6 | G73: 6 | P73: =COUNT(D73:N73) | Q73: =SUM(D73:N73) | R73: =IF(P73<=4,"OK","Too many") | S73: Cheaper, since taxes now wait for it (step 2, question 9). | T73: Let's make all Manor buildings have to be contigous to a manor building or a decorations contiguous to a manor building and work in an art that make the whole Manor area grass merge, so it forms a "single" dirt silhouette
A74: Manor House (enlarge) | B74: Manor | C74: 40 timber, 20 stone, 50 coins | D74: 4 | E74: 10 | G74: 10 | O74: 12 | P74: =COUNT(D74:N74) | Q74: =SUM(D74:N74) | R74: =IF(P74<=4,"OK","Too many")
A75: Stone Manor (enlarge) | B75: Manor | C75: 40 planks, 40 dressed stone, 20 stone, 150 coins | G75: 5 | H75: 10 | I75: 10 | O75: 40 | P75: =COUNT(D75:N75) | Q75: =SUM(D75:N75) | R75: =IF(P75<=4,"OK","Too many")
A76: Lord's Stable | B76: Manor | C76: 40 timber, 20 planks, 120 coins | D76: 10 | E76: 5 | O76: 30 | P76: =COUNT(D76:N76) | Q76: =SUM(D76:N76) | R76: =IF(P76<=4,"OK","Too many")
A77: Watch Tower | B77: Manor | C77: 20 stone, 10 planks, 40 coins | E77: 3 | G77: 10 | I77: 6 | P77: =COUNT(D77:N77) | Q77: =SUM(D77:N77) | R77: =IF(P77<=4,"OK","Too many") | T77: Limit to 2 x city_level_above_village
A78: Manor Garden | B78: Manor | C78: 60 stone, 30 planks, 900 coins | E78: 8 | G78: 15 | H78: 6 | O78: 200 | P78: =COUNT(D78:N78) | Q78: =SUM(D78:N78) | R78: =IF(P78<=4,"OK","Too many")
A79: Town wall (a section) | B79: Manor | C79: 4 stone, 2 dressed stone | G79: 6 | P79: =COUNT(D79:N79) | Q79: =SUM(D79:N79) | R79: =IF(P79<=4,"OK","Too many")
A80: Great Works (revisited in step 5)
A81: Statue | B81: Great Works | C81: 20 dressed stone, 2 tools, 150 coins | H81: 5 | M81: 1 | O81: 50 | P81: =COUNT(D81:N81) | Q81: =SUM(D81:N81) | R81: =IF(P81<=4,"OK","Too many")
A82: Bell Tower | B82: Great Works | C82: 60 stone, 40 dressed stone, 20 planks, 1200 coins | E82: 5 | G82: 30 | H82: 10 | O82: 100 | P82: =COUNT(D82:N82) | Q82: =SUM(D82:N82) | R82: =IF(P82<=4,"OK","Too many")
A83: Covered Market Hall | B83: Great Works | C83: 30 dressed stone, 25 planks, 20 tiles, 250 coins | E83: 6 | H83: 20 | I83: 30 | O83: 50 | P83: =COUNT(D83:N83) | Q83: =SUM(D83:N83) | R83: =IF(P83<=4,"OK","Too many")
A84: Cathedral | B84: Great Works | C84: 180 dressed stone, 120 stone, 100 planks, 60 tiles, 25 tools, 1500 coins | H84: 45 | J84: 15 | L84: 8 | M84: 6 | O84: 250 | P84: =COUNT(D84:N84) | Q84: =SUM(D84:N84) | R84: =IF(P84<=4,"OK","Too many") | S84: Had six materials (G12): plain stone, planks and tiles give way to mortar and stained glass.
A85: University | B85: Great Works | C85: 60 dressed stone, 40 planks, 30 tiles, 10 books, 500 coins | E85: 30 | H85: 20 | I85: 30 | N85: 10 | O85: 150 | P85: =COUNT(D85:N85) | Q85: =SUM(D85:N85) | R85: =IF(P85<=4,"OK","Too many")
A86: Guildhall | B86: Great Works | C86: 100 dressed stone, 80 planks, 40 tiles, 15 tools, 4000 coins | H86: 25 | I86: 40 | J86: 12 | L86: 6 | O86: 400 | P86: =COUNT(D86:N86) | Q86: =SUM(D86:N86) | R86: =IF(P86<=4,"OK","Too many")
A87: Decorations and backyards
A88: Flower Garden | B88: Decor | C88: 5 timber, 25 coins | D88: 1 | O88: 5 | P88: =COUNT(D88:N88) | Q88: =SUM(D88:N88) | R88: =IF(P88<=4,"OK","Too many")
A89: Flower Bed | B89: Decor | C89: 4 coins | O89: 2 | P89: =COUNT(D89:N89) | Q89: =SUM(D89:N89) | R89: =IF(P89<=4,"OK","Too many")
A90: Clipped Hedge | B90: Decor | C90: 3 coins | O90: 2 | P90: =COUNT(D90:N90) | Q90: =SUM(D90:N90) | R90: =IF(P90<=4,"OK","Too many")
A91: Wayside Shrine | B91: Decor | C91: 2 timber, 2 stone, 6 coins | D91: 1 | G91: 1 | O91: 2 | P91: =COUNT(D91:N91) | Q91: =SUM(D91:N91) | R91: =IF(P91<=4,"OK","Too many")
A92: Stone Fountain | B92: Decor | C92: 6 stone, 15 coins | G92: 2 | O92: 10 | P92: =COUNT(D92:N92) | Q92: =SUM(D92:N92) | R92: =IF(P92<=4,"OK","Too many")
A93: Public Garden | B93: Decor | C93: 10 timber, 10 stone, 120 coins | D93: 3 | G93: 3 | O93: 30 | P93: =COUNT(D93:N93) | Q93: =SUM(D93:N93) | R93: =IF(P93<=4,"OK","Too many")
A94: Maypole | B94: Decor | C94: 15 timber, 60 coins | D94: 4 | O94: 15 | P94: =COUNT(D94:N94) | Q94: =SUM(D94:N94) | R94: =IF(P94<=4,"OK","Too many")
A95: Vegetable patch (backyard) | B95: Decor | C95: 4 timber, 8 coins | E95: 3 | O95: 10 | P95: =COUNT(D95:N95) | Q95: =SUM(D95:N95) | R95: =IF(P95<=4,"OK","Too many")
A96: Hen coop (backyard) | B96: Decor | C96: 8 timber, 15 coins | E96: 3 | O96: 10 | P96: =COUNT(D96:N96) | Q96: =SUM(D96:N96) | R96: =IF(P96<=4,"OK","Too many")
A97: Beehives (backyard) | B97: Decor | C97: 6 timber, 25 coins | E97: 5 | O97: 12 | P97: =COUNT(D97:N97) | Q97: =SUM(D97:N97) | R97: =IF(P97<=4,"OK","Too many")
A98: Flower boxes (house) | B98: Decor | C98: 6 coins | O98: 3 | P98: =COUNT(D98:N98) | Q98: =SUM(D98:N98) | R98: =IF(P98<=4,"OK","Too many")
A99: Roads and zones
A100: Stone road (per tile) | B100: Roads | C100: 2 stone | G100: 2 | P100: =COUNT(D100:N100) | Q100: =SUM(D100:N100) | R100: =IF(P100<=4,"OK","Too many") | S100: Per 2 tiles in practice: half a stone a tile, rounded when laid.
A101: Cobbled street (per tile) | B101: Roads | C101: 1 dressed stone | H101: 2 | P101: =COUNT(D101:N101) | Q101: =SUM(D101:N101) | R101: =IF(P101<=4,"OK","Too many") | S101: Per 4 tiles in practice.
...

Sheet 2 Upkeep
A1: Upkeep: tools and wood parts worn a year at a full crew
A2: Today's rates read from the game; proposed rates in blue. Simple buildings wear at most a tool a year (your note).
A4: Building | B4: Kind | C4: Wears | D4: Today a month | E4: Today a year | F4: Proposed a year | G4: Proposed a month | H4: Change | I4: Your notes
A5: Simple buildings (at most 1 a year)
A6: Woodcutter's Lodge | B6: Simple buildings | C6: tools | D6: 0.15 | E6: =D6*12 | F6: 1 | G6: =F6/12
A7: Forester's Hut | B7: Simple buildings | C7: tools | D7: 0.05 | E7: =D7*12 | F7: 0.5 | G7: =F7/12
A8: Stone Quarry | B8: Simple buildings | C8: tools | D8: 0.2 | E8: =D8*12 | F8: 1.5 | G8: =F8/12
A9: Clay Pit | B9: Simple buildings | C9: tools | D9: 0.05 | E9: =D9*12 | F9: 0.5 | G9: =F9/12
A10: Sand Pit | B10: Simple buildings | C10: tools | D10: 0.05 | E10: =D10*12 | F10: 0.5 | G10: =F10/12
A11: Farmstead | B11: Simple buildings | C11: tools | D11: 0.1 | E11: =D11*12 | F11: 1 | G11: =F11/12
A12: Orchard Keeper's Lodge | B12: Simple buildings | C12: tools | D12: 0.05 | E12: =D12*12 | F12: 0.5 | G12: =F12/12
A13: Sawpit | B13: Simple buildings | C13: tools | D13: 0.15 | E13: =D13*12 | F13: 1 | G13: =F13/12
A14: Village workshops
A15: Windmill | B15: Village workshops | C15: wood parts | D15: 0.25 | E15: =D15*12 | F15: 3 | G15: =F15/12
A16: Watermill | B16: Village workshops | C16: wood parts | D16: 0.3 | E16: =D16*12 | F16: 6 | G16: =F16/12
A17: Brewhouse | B17: Village workshops | C17: wood parts | D17: 0.05 | E17: =D17*12 | F17: 1 | G17: =F17/12
A18: Weaver | B18: Village workshops | C18: wood parts | D18: 0.1 | E18: =D18*12 | F18: 1.5 | G18: =F18/12
A19: Dyer's Workshop | B19: Village workshops | C19: wood parts | D19: 0.05 | E19: =D19*12 | F19: 2 | G19: =F19/12
A20: Potter's Workshop | B20: Village workshops | C20: wood parts | D20: 0.1 | E20: =D20*12 | F20: 2 | G20: =F20/12
A21: Trading Post | B21: Village workshops | C21: wood parts | D21: 0.1 | E21: =D21*12 | F21: 0 | G21: =F21/12 | H21: No upkeep (your edit).
A22: Dock | B22: Village workshops | C22: wood parts | D22: 0.2 | E22: =D22*12 | F22: 3 | G22: =F22/12
A23: Winery | B23: Village workshops | C23: wood parts | D23: 0.15 | E23: =D23*12 | F23: 4 | G23: =F23/12
A24: Town workshops
A25: Carpenter's Workshop | B25: Town workshops | C25: tools | D25: 0.1 | E25: =D25*12 | F25: 4 | G25: =F25/12
A26: Cooper's Workshop | B26: Town workshops | C26: tools | D26: 0.1 | E26: =D26*12 | F26: 8 | G26: =F26/12
A27: Stonemason's Yard | B27: Town workshops | C27: tools | D27: 0.2 | E27: =D27*12 | F27: 10 | G27: =F27/12
A28: Tile Kiln | B28: Town workshops | C28: tools | D28: 0.05 | E28: =D28*12 | F28: 2 | G28: =F28/12
A29: Lime Kiln | B29: Town workshops | C29: tools | D29: 0.05 | E29: =D29*12 | F29: 2 | G29: =F29/12
A30: Charcoal Burner | B30: Town workshops | C30: tools | D30: 0.05 | E30: =D30*12 | F30: 1 | G30: =F30/12
A31: Glassworks | B31: Town workshops | C31: tools | D31: 0.1 | E31: =D31*12 | F31: 9 | G31: =F31/12
A32: Bog Iron Pit | B32: Town workshops | C32: tools | D32: 0.25 | E32: =D32*12 | F32: 2 | G32: =F32/12
A33: Bloomery | B33: Town workshops | C33: tools | D33: 0.1 | E33: =D33*12 | F33: 5 | G33: =F33/12
A34: Blacksmith | B34: Town workshops | C34: tools | D34: 0.1 | E34: =D34*12 | F34: 6 | G34: =F34/12
A35: Armoury | B35: Town workshops | C35: tools | D35: 0.15 | E35: =D35*12 | F35: 6 | G35: =F35/12 | H35: Moves to the manor (step 5).
A36: Jeweller's Shop | B36: Town workshops | C36: tools | D36: 0.1 | E36: =D36*12 | F36: 10 | G36: =F36/12
A37: Tannery | B37: Town workshops | C37: tools | D37: 0.05 | E37: =D37*12 | F37: 1 | G37: =F37/12
A38: Tailor & Cobbler | B38: Town workshops | C38: tools | D38: 0.05 | E38: =D38*12 | F38: 3 | G38: =F38/12
A39: Builder's Yard (its ox cart) | B39: Civic | C39: wood parts | D39: 1 | E39: =D39*12 | F39: 8 | G39: =F39/12 | H39: A wood part every three months instead of every month.
A41: Settlers' tools: two years of a regular set of simple buildings
A42: Woodcutter | B42: 2 | C42: =B42*SUMIF($A$5:$A$39,"Woodcutter's Lodge",$F$5:$F$39)*2
A43: Stone Quarry | B43: 1 | C43: =B43*SUMIF($A$5:$A$39,"Stone Quarry",$F$5:$F$39)*2
A44: Sawpit | B44: 1 | C44: =B44*SUMIF($A$5:$A$39,"Sawpit",$F$5:$F$39)*2
A45: Farmstead | B45: 1 | C45: =B45*SUMIF($A$5:$A$39,"Farmstead",$F$5:$F$39)*2
A46: Forester's Hut | B46: 0 | C46: =B46*SUMIF($A$5:$A$39,"Forester's Hut",$F$5:$F$39)*2
A47: Tools to bring (two years) | C47: =ROUNDUP(SUM(C42:C46),0)
A48: Today the settlers bring 6 tools and 2 wood parts.

Sheet Crew audit
A1: What scales with the crew today (code check)
A2: Read from the game's code as it stands. Rows marked "No" are fixed in the rework (G20).
A4: What | B4: Scales with crew today? | C4: How it works now | D4: In the rework
A5: Workshop and gatherer output | B5: Yes | C5: Work per day = filled places / places, times walking efficiency, mood, learning and worn gear. | D5: Keep.
A6: Upkeep (tools, wood parts) | B6: Yes | C6: Wear per day = rate times filled share of the crew. | D6: Keep.
A7: Farm fields | B7: Yes | C7: Crop growth = farmers at work / tiles to tend. | D7: Keep.
A8: Herds | B8: Yes | C8: Herders' share of the crew scales the yield. | D8: Keep.
A9: Orchard picking | B9: Yes | C9: Fruit picked = pickers times a daily rate. | D9: Keep.
A10: Market stalls | B10: Yes | C10: Each stallholder opens one stall serving ten households. | D10: Keep; maximum stalls also depend on space (your note).
A11: Alehouse / tavern | B11: No | C11: Pours for every home in reach as soon as one tapster works. | D11: Homes served by tapsters at work (your note).
A12: Trading post and dock | B12: No | C12: Full monthly cargo with a single worker. | D12: Cargo by the crew at work.
A13: Storehouse and granary haulers | B13: No | C13: One hauler anywhere and every workplace's goods are fetched. | D13: Each hauler fetches so many loads a day.
A14: Builder's yard | B14: No | C14: Full speed-up with any worker and its ox. | D14: Speed-up by the crew at work.
A15: Monastery, university | B15: No | C15: Fed with books and anyone at work: full knowledge and prestige. | D15: Knowledge by the crew at work.
... A18: Stable, watchtower | B18: No | C18: One groom or watchman: on or off. | D18: Fine with one place; stays.

Sheet 3 Mixed & late
A1: Step 3: mixed industry and late goods
A2: Workshops that join two lines, and the goods at the end of every chain. Same gate rule (G6).
A4: Line | B4: Unlock | C4: Kind | D4: Makes | E4: From | F4: Gate | G4: Knowledge | H4: Upkeep | I4: Essential for | J4: Why | K4: Change from today | L4: Your notes
A5: Garments | B5: Embroiderer | C5: Building | D5: fine clothes | E5: cloth, dyes | G5: 10 | H5: tools | I5: Patrician House | J5: Fine clothes get their own building (G16): dyed cloth, embroidered. | K5: Was a tailor recipe.
A6: Glass | B6: Glazier's Workshop | C6: Building | D6: stained glass | E6: glass, dyes | G6: 10 | H6: tools | I6: Patrician House | J6: Coloured panes leaded into windows: churches, the cathedral, the finest homes. | K6: Was a glassworks recipe.
A7: Writing | B7: Tanner: parchment | C7: Recipe | D7: parchment | E7: hides | G7: 3 | J7: A second writing material: feeds offices and books as well as paper does, but costs hides. | K7: New good. Hides get a second use.
A8: Writing | B8: Scriptorium (charter) | C8: Building | D8: books, knowledge | E8: paper or parchment, leather | F8: charter | H8: tools | J8: Books stay a charter craft; other towns buy them. | K8: Books from parchment as well as paper.
A9: Drink | B9: Brewhouse: mead | C9: Recipe | D9: mead | E9: honey + fuel | G9: 3 | J9: With the beekeeper every town has honey; mead becomes a third tavern drink. | K9: Was charter-only. Meadmakers now doubles honey and mead instead.
A10: Drink | B10: Winery (charter) | C10: Building | D10: wine | E10: grapes, crates | F10: charter | H10: wood parts | J10: Wine stays the orchard charter's prize: a luxury and a drink.
A11: Metal | B11: Cooper (hoops) | C11: Building | D11: crates | E11: planks, iron | G11: 3 | H11: wood parts | J11: Iron hoops bind the staves: iron's second use. | K11: Iron added (your edit). Waits for trade (G7 exception).
A12: Metal | B12: Jeweller's Shop (charter) | C12: Building | D12: jewellery | E12: silver, glass | F12: charter | H12: tools | J12: Silver set with glass beads; silver is bought or comes with Deep Veins. | K12: Glass added as a second input.
A14: Removed: arms (the armoury becomes a manor building, step 5), oats, mushrooms. Not added on purpose: new raw goods. Silver stays bought (or the Deep Veins charter).

Sheet 3 Goods map
A1: Step 3: every good after the rework, its source and its uses
A2: Built by hand from steps 1-3. G14: foods are used by being eaten, intermediates need their chain, finished goods two uses.
A4: Good | B4: Kind | C4: Made by | D4: Used by | E4: Uses | F4: G14 | G4: Your notes
A5: Building materials
A6: Timber | B6: material | C6: Woodcutter | D6: build costs; sawmill; charcoal burner; blacksmith | E6: 4 | F6: OK
A7: Firewood | B7: fuel | C7: Woodcutter | D7: home heating; fuel for every fire workshop (G18) | E7: 2 | F7: OK
A8: Planks | B8: material | C8: Sawmill | D8: build costs; carpenter; cooper | E8: 3 | F8: OK
A9: Wood parts | B9: material | C9: Carpenter | D9: build costs; upkeep | E9: 2 | F9: OK
A10: Stone | B10: material | C10: Quarry | D10: build costs; stonemason; lime kiln; stone roads | E10: 4 | F10: OK
A11: Dressed stone | B11: material | C11: Stonemason | D11: build costs; cobbled streets | E11: 2 | F11: OK
A12: Clay | B12: intermediate | C12: Clay Pit | D12: kiln; potter | E12: 2 | F12: OK
A13: Tiles | B13: material | C13: Kiln | D13: build costs (homes, churches, civic) | E13: 1 | F13: OK: many build costs
A14: Sand | B14: intermediate | C14: Sand Pit | D14: lime kiln; glassworks | E14: 2 | F14: OK
A15: Mortar | B15: material | C15: Lime Kiln | D15: build costs: Merchant's and Patrician houses, churches, monastery, courthouse, cathedral | E15: 1 | F15: OK: many build costs
A16: Charcoal | B16: fuel | C16: Charcoal Burner | D16: fuel (worth two firewood); glassworks | E16: 2 | F16: OK
A17: Glass | B17: material / luxury | C17: Glassworks | D17: build costs; glazier; jeweller; luxury | E17: 4 | F17: OK
... A23: Silver | B23: intermediate | C23: bought; Deep Veins charter | D23: jeweller | E23: 1 | F23: OK: feeds one chain
A24: Food
A25: Bread | B25: food | C25: Bakery | D25: eaten | E25: 1 | F25: OK: food
A26: Vegetables | B26: food | C26: Farmstead fields; vegetable patch | D26: eaten | E26: 1 | F26: OK: food
A27: Meat | B27: food | C27: Hunter; herds | D27: eaten | E27: 1 | F27: OK: food
A28: Pork | B28: food | C28: Herds | D28: eaten | E28: 1 | F28: OK: food
A29: Fish | B29: food | C29: Fisher | D29: eaten | E29: 1 | F29: OK: food
A30: Eggs | B30: food | C30: Hen coop | D30: eaten | E30: 1 | F30: OK: food
A31: Berries | B31: food | C31: Forager | D31: eaten; dyer | E31: 2 | F31: OK: food
A32: Apples | B32: food | C32: Orchards | D32: eaten; cider | E32: 2 | F32: OK: food
A33: Pears | B33: food | C33: Orchards | D33: eaten | E33: 1 | F33: OK: food
A34: Plums | B34: food | C34: Orchards | D34: eaten | E34: 1 | F34: OK: food
A35: Grapes | B35: food | C35: Vines (charter) | D35: eaten; winery | E35: 2 | F35: OK: food
A36: Honey | B36: food | C36: Beekeeper; hives | D36: eaten; mead | E36: 2 | F36: OK: food
... A38: Cheese | B38: food | C38: Dairy | D38: eaten | E38: 1 | F38: OK: food
A39: Farm and craft goods
A40: Grain | B40: intermediate | C40: Wheat fields | D40: windmill, watermill | E40: 1 | F40: OK: feeds one chain
A41: Barley | B41: intermediate | C41: Barley fields | D41: brewhouse | E41: 1 | F41: OK: feeds one chain
A42: Flour | B42: intermediate | C42: Mills | D42: bakery | E42: 1 | F42: OK: feeds one chain
A43: Flax | B43: intermediate | C43: Flax fields | D43: weaver; paper mill | E43: 2 | F43: OK
A44: Wool | B44: intermediate | C44: Sheep | D44: weaver | E44: 1 | F44: OK: feeds one chain
A45: Hides | B45: intermediate | C45: Hunter; herds | D45: tanner (leather, parchment) | E45: 2 | F45: OK
A46: Leather | B46: intermediate | C46: Tanner | D46: tailor (boots); scriptorium (bindings) | E46: 2 | F46: OK
A47: Cloth | B47: intermediate | C47: Weaver | D47: tailor; embroiderer | E47: 2 | F47: OK
A48: Woad | B48: intermediate | C48: Woad fields | D48: dyer | E48: 1 | F48: OK: feeds one chain
A49: Dyes | B49: intermediate | C49: Dyer | D49: embroiderer; glazier; potter | E49: 3 | F49: OK
A50: Herbs | B50: intermediate | C50: Forager | D50: apothecary; weak medicine for homes | E50: 2 | F50: OK
A51: Paper | B51: writing | C51: Paper Mill | D51: tax offices and courthouse; scriptorium | E51: 2 | F51: OK
A52: Parchment | B52: writing | C52: Tanner (new recipe) | D52: tax offices and courthouse; scriptorium | E52: 2 | F52: OK
A53: Finished goods
A54: Clothes | B54: need | C54: Tailor | D54: Townhouse and Merchant's House need; courthouse watch (proposal) | E54: 2 | F54: OK
A55: Boots | B55: need | C55: Tailor | D55: Townhouse (either garment) and Merchant's House need; courthouse watch (proposal) | E55: 2 | F55: OK
A56: Medicine | B56: need | C56: Apothecary | D56: home need; sickness events | E56: 2 | F56: OK
A57: Ale | B57: drink | C57: Brewhouse | D57: alehouse and tavern; harvest feast | E57: 2 | F57: OK
A58: Cider | B58: drink | C58: Brewhouse | D58: alehouse and tavern; harvest feast | E58: 2 | F58: OK
A59: Mead | B59: drink | C59: Brewhouse | D59: alehouse and tavern; harvest feast | E59: 2 | F59: OK
A60: Wine | B60: luxury / drink | C60: Winery (charter) | D60: luxury; tavern drink | E60: 2 | F60: OK
A61: Fine clothes | B61: luxury | C61: Embroiderer | D61: luxury; Patrician House need | E61: 2 | F61: OK
A62: Fine pottery | B62: luxury | C62: Potter | D62: luxury | E62: 1 | F62: OK: luxury (+ export)
A63: Jewellery | B63: luxury | C63: Jeweller (charter) | D63: luxury | E63: 1 | F63: OK: luxury (+ export)
A64: Books | B64: learning | C64: Scriptorium (charter) or bought | D64: monastery; university (cost and monthly) | E64: 2 | F64: OK

Sheet 4 Mechanics
A1: Step 4: the kinds of depth an industry can get
A2: Five kinds, each a different sort of decision. Mark each Agree / Change / Drop.
A4: ID | B4: Kind | C4: How it works | D4: The decision it creates | E4: Your call | F4: Your notes | G4: Status
A5: M1 | B5: Extension | C5: A small add-on built on a free tile touching its workplace. A workplace may have several different extensions, each built once. An extension adds an ability and may also add a flat bonus; it often runs on a consumable, and shows in the art. | D5: Where to spend tiles and upkeep, workplace by workplace. | E5: Change | F5: Each extension can be built once per workplace, but one workplace can have more than one possible extension. Can also add a flat bonus besides na ability | G5: Revised to your note
A6: M2 | B6: Upgrade | C6: The workplace is rebuilt in place with a new look. Upgrades usually add places and another bonus together (ratio, ability). A kind of workplace may have a chain of upgrades; for now each has one. | D6: Pay finer materials now to save raw ones later. | E6: Change | F6: Some may have a chain of upgrades. The or heve is not excludent, usually gain workplaces AND some other bonuses | G6: Revised to your note
A7: M3 | B7: Choice | C7: A town-wide pair (sometimes three) of exclusive ways of working, picked once. | D7: What kind of town this is; no going back. | E7: Agree
A8: M4 | B8: Variant | C8: A new crop, animal, breed or recipe for a building the town already has. | D8: Fit the land: poor soil, scrub, river. | E8: Agreed
A9: M5 | B9: Town option | C9: A cosmetic town-wide look with a small effect and a running cost; it can be switched off. | D9: Personalise the town, at a price. | E9: Agreed
A10: M6 | B10: Prices | C10: Knowledge in proportion to the bonus (G8). Learning by doing is required for upgrades and extensions, optional for variants and choices. | E10: Change | F10: Learning by doing optional for variant and choice. Only mandatory for upgrades and extensions | G10: Revised to your note

Sheet 4 Depth
A1: Step 4: upgrades, extensions, choices and options for every line
A2: Costs on the new scale (2 Costs); knowledge in blue. Each entry changes how the line works, not just how much it makes.
A4: Line | B4: Name | C4: Kind | D4: Of | E4: What it changes | F4: Runs on | G4: Cost | H4: Knowledge | I4: Condition | J4: Why (the decision) | K4: Your notes | L4: My notes
A5: Timber
A6: Timber | B6: Coppice or high forest | C6: Choice | D6: town | E6: Coppice: foresters' woods regrow twice as fast, but woodcutters fell poles (firewood half again, timber a third less). High forest: timber a fifth more, regrowth as today. | H6: 6 | I6: 200 timber felled | J6: A fuel town or a building town.
A7: Timber | B7: Large woodcutters lodge | C7: Upgrade | D7: Woodcutters | E7: 2 more working spaces | G7: 6 timber | H7: 4 | I7: 100 timber felled
A8: Timber | B8: Ox tool-shed | C8: Extension | D8: Woodcutters | E8: Remove penalties for moving through the woods and reduce carrying timber | F8: 0.5 tool a year | G8: 2 timber, 2 planks, 1 tile | H8: 4 | I8: 150 timber felled | K8: Does not house the ox, still need stables
A9: Timber | B9: Water sawmill | C9: Building | D9: Sawmill | E9: Beside water: one timber makes one plank (today four make three). | F9: 2 wood parts a year | G9: 6 planks, 4 wood parts, 4 stone | H9: 8 | J9: Saves timber once planks are the bottleneck; ties the sawmill to the river. | K9: This would work better as a unlockable building | L9: Now a building of its own (your note), unlocked by knowledge.
A10: Timber | B10: Lathe | C10: Extension | D10: Carpenter | E10: Wood parts from two planks instead of three. | F10: 1 tool a year | G10: 4 planks, 2 tools, 1 tile | H10: 6 | I10: 100 wood parts made | J10: Cheaper upkeep for every mill in town.
A11: Timber | B11: Tree nursery | C11: Extension | D11: Forester | E11: Also raises saplings: orchards in its reach bear a season sooner. | G11: 4 timber, 2 planks, no tile, just add props in the building | H11: 4 | I11: 50 trees planted | J11: Links the woods to the orchards.
A12: Stone & earth
A13: Stone & earth | B13: Quarry crane | C13: Extension | D13: Quarry | E13: One more place, and one stone in five comes out ready-dressed. | F13: 1 wood part a year | G13: 4 planks, 2 wood parts | H13: 8 | I13: 50 stone gathered | J13: A little dressed stone without a mason.
A14: Stone & earth | B14: Stone street | C14: Upgrade | D14: Dirt path | E14: same as before | G14: 2 stone/tile | H14: 2
A15: Stone & earth | B15: Coblestone street | C15: Upgrade | D15: Dirt path | E15: same as before | G15: 2 dressed stone/tile | H15: 4 | I15: Stone street unlocked | L15: Roads move behind knowledge: fine with G6.
A16: Stone & earth | B16: Mason's lodge | C16: Upgrade | D16: Stonemason | E16: The masons also work on Great Works in reach: they rise a fifth faster. | G16: 2 dressed stone, 2 tiles | H16: 8 | I16: a Great Work begun | J16: Where to put the masons.
A17: Stone & earth | B17: Second firing chamber | C17: Extension | D17: Kiln | E17: Tiles on half the fuel. | G17: 6 stone, 2 tiles | H17: 5 | I17: 100 tiles fired | J17: Fuel or tiles.
A18: Stone & earth | B18: Limewash | C18: Town option | D18: Lime Kiln | E18: Homes may be limewashed white: +1 beauty to the home itself; each painted home takes 0.5 mortar a year. | F18: 0.5 mortar a year | H18: 4 | J18: A white town, at a running cost.
A19: Grain & farming
A20: Grain & farming | B20: Rye | C20: Variant | D20: Fields | E20: Grows on poor soil as well as rich, but yields half as much as wheat; milled like wheat. | H20: 3 | J20: A way to farm bad land.
A21: Grain & farming | B21: Beans | C21: Variant | D21: Fields | E21: Vegetables that feed the soil: next year's crop on that field a fifth more. | H21: 4 | J21: Rotation becomes a plan.
A22: Grain & farming | B22: Iron plough | C22: Extension | D22: Farmstead | E22: Farmers tend half as many fields again. | F22: 1 tool a year | G22: 4 planks, 2 tools | H22: 6 | I22: 100 grain harvested | J22: Fewer farmers, more tools. Overlaps the Heavy Plough charter (step 6).
A23: Grain & farming | B23: Tower mill | C23: Upgrade | D23: Windmill | E23: Four grain make five flour. | G23: 8 stone, 4 wood parts, 4 tiles | H23: 8 | I23: 200 flour milled | J23: Stone for flour.
A24: Grain & farming | B24: Brewer's second copper | C24: Upgrade | D24: Brewhouse | E24: Brews two drinks at once. | G24: 6 planks, 4 stone | H24: 6 | I24: two drinks learned | J24: Variety in the taverns from one building.
A25: Herds
A26: Herds | B26: Goats | C26: Variant | D26: Animal Farm | E26: Milk on scrub: a goat needs only one tile, but gives little milk. | H26: 3 | J26: Dairy without good pasture.
A27: Herds | B27: Long-wool sheep | C27: Variant | D27: Animal Farm | E27: Half as much wool again | H27: 8 | I27: 200 wool shorn
A28: Herds | B28: Frisian cattle | C28: Variant, choice | D28: Animal Farm | E28: Twice as much milk, but 30% less meat | H28: 12 | I28: 30 livestock | J28: choice with the other cattle breed | L28: Holstein and Wagyu are modern names. Suggest Frisian (milk) and Highland (beef). (5 Questions)
A29: Herda | B29: Highland cattle | C29: Variant, choice | D29: Animal Farm | E29: Twice as much meat, but less milk | H29: 12 | I29: 30 livestock | L29: See row 28.
A30: Herds | B30: Animal sheds | C30: Upgrade | D30: Pasture | E30: Increase pasture space by 15% | G30: 10 planks | H30: 6 | I30: 15 livestock
A31: Herds | B31: Cheese cellar | C31: Upgrade | D31: Dairy | E31: Two milk make two cheese (today three make two). | G31: 6 stone, 2 tiles | H31: 6 | I31: 30 cheese made
A32: Orchards & hives
A33: Orchards & hives | B33: Espalier | C33: Choice | D33: town | E33: Trees trained on walls: orchard tiles touching walls or buildings bear a third more; open orchards as today. | H33: 8 | J33: A placement puzzle for compact towns.
A34: Orchards & hives | B34: Pears | C34: Variant | D34: Orchard | E34: Takes 1 more year to mature, but yield a third more | H34: 6 | L34: Pears move here; plums stay in step 1.
A35: Orchards & hives | B35: Strawberries | C35: Variant | D35: Orchard | E35: Mature in one year, and yield a fifth more | H35: 12 | L35: A new good: strawberries (food), your answer.
A36: Orchards & hives | B36: Skep or log hives | C36: Choice | D36: town | E36: Skeps: more honey, bees swarm away now and then. Log hives: steady but less bonus. | H36: 5 | J36: Risk or steadiness.
A37: Wild food & herbs
A38: Wild food & herbs | B38: Herb garden | C38: Extension | D38: Forager | E38: Herbs grown on a plot all year instead of gathered in season. | G38: 3 planks | H38: 3 | I38: 50 herbs gathered | J38: Steady medicine.
A39: Wild food & herbs | B39: Fishing boat | C39: Upgrade | D39: Fisher | E39: One more working place | F39: 1 wood parts a year | G39: 6 planks, 2 wood parts | H39: 6 | I39: 50 fish caught
A40: Wild food & herbs | B40: Pisciculture | C40: Extension | D40: Fisher | E40: Create a fixed fish school close to the fisher hut | G40: 1 timber, 4 planks | H40: 6 | I40: 100 fish caught | L40: Spelling: Pisciculture.
A41: Wild food & herbs | B41: Kennels | C41: Extension | D41: Hunter | E41: Double walking speed for hunters; the dogs eat a meat a month. | F41: 1 meat a month | G41: 4 timber, 2 planks | H41: 4 | I41: 100 meat hunted
A42: Cloth & leather
A43: Cloth & leather | B43: Broadloom | C43: Upgrade | D43: Weaver | E43: Two wool or three flax make three cloth (today two). | F43: 1 wood part a year | G43: 6 planks, 4 wood parts | H43: 8 | I43: 100 cloth woven
A44: Cloth & leather | B44: Dyed tunics | C44: Town option | D44: Dyer | E44: Villagers wear dyed colours (the lord's, or each home's): +2 happiness; a dye a year for every ten villagers. | F44: dyes | H44: 4 | J44: A colourful town, at a running cost.
A45: Cloth & leather | B45: Cobbler | C45: Building | D45: Tailor | E45: A shop for boots alone, faster than the tailor's recipe. | F45: 1 tool a year | G45: 4 timber, 6 planks | H45: 6 | J45: Split garments when the town needs both.
A46: Iron & tools
A47: Iron & tools | B47: Water bellows | C47: Extension | D47: Bloomery | E47: Beside water: iron on half the fuel. | F47: 2 wood parts a year | G47: 6 planks, 4 wood parts | H47: 10 | I47: 100 iron smelted | J47: River towns smelt cheaply.
A48: Iron & tools | B48: Farrier | C48: Extension | D48: Blacksmith | E48: Shoes the draught animals: a pack horse carries a quarter more, an ox speeds building a quarter more. | F48: 1 iron a year per animal | G48: 4 planks, 2 stone | H48: 6 | I48: a draught animal at work | J48: Links smithing to trade and building.
A49: Iron & tools | B49: Deep shaft | C49: Extension | D49: Bog Iron Pit | E49: The ore lasts twice as long. | G49: 6 planks, 4 wood parts | H49: 6 | I49: 200 ore dug
A50: Glass & writing
A51: Glass & writing | B51: Crown glass | C51: Upgrade | D51: Glassworks | E51: Three sand and two charcoal make two glass (today one). | G51: 8 stone, 4 tools | H51: 12 | I51: 50 glass made
A52: Glass & writing | B52: Church windows | C52: Town option | D52: Glazier | E52: Churches and the cathedral get stained-glass windows: +happiness and prestige; a stained glass each, once. | F52: stained glass (once) | H52: 2 | J52: Show off the glazier.
A53: Glass & writing | B53: Second vat | C53: Upgrade | D53: Paper Mill | E53: One flax makes two paper. | G53: 6 planks, 2 wood parts | H53: 6 | I53: 100 paper made
A54: Civic
A55: Civic | B55: Sunday school | C55: Extension | D55: Church | E55: 0.02 knowledge a month for each home it serves; all work 2% slower. | G55: 4 planks, 2 tiles | H55: 4 | I55: the church serving 10 homes | J55: Learning grows with the parish (the public school is the fixed alternative).
A56: Civic | B56: Infirmary | C56: Extension | D56: Monastery | E56: Sickness passes lightly over homes in reach; uses medicine. | F56: 1 medicine a month | G56: 6 stone, 4 tiles | H56: 8 | I56: 20 medicine made | J56: Where medicine goes beyond the homes.
A57: Civic | B57: Inn rooms | C57: Upgrade | D57: Tavern | E57: Travellers stay: coins every month; they eat a little food. | F57: food | G57: 6 planks, 4 tiles | H57: 6 | I57: the tavern serving 10 homes | J57: A tavern that earns.
A58: Civic | B58: Loft | C58: Upgrade | D58: Storehouse / Granary | E58: Holds half as much again. | G58: 6 planks | H58: 4 | I58: the store full once | L58: With the improved stores below this becomes a chain: Loft, then Improved (M2).
A59: Civic | B59: Pump | C59: Upgrade | D59: Well | E59: Reach half as far again. | F59: 1 wood part a year | G59: 2 wood parts, 2 stone | H59: 3 | I59: the well serving 8 homes
A60: Civic | B60: Market cross | C60: Extension | D60: Market | E60: +beauty around it, and each stall serves two more homes. | G60: 4 dressed stone | H60: 5 | I60: a market of 4 stalls
A61: Trade
A62: Trade | B62: Toll navigation | C62: Upgrade (town, step 1 of 2) | E62: reduce import costs multiplier by a factor of 0,1 and increase export multiplier by a factor of 0,1 | H62: 12 | I62: 250 goods traded | L62: Same effect on all trade, so not a choice: two steps that stack (your answer).
A63: Trade | B63: Trade deals | C63: Upgrade (town, step 2 of 2) | E63: reduce import costs multiplier by a factor of 0,1 and increase export multiplier by a factor of 0,1 | H63: 12 | I63: 500 goods traded | L63: Second step: needs the first.
A64: Trade | B64: Goods cart | C64: Extension | D64: Trading post | E64: Allow the builg of a horse to increase carrying capacity by 40 (total) | F64: 1 wood part a year | G64: 10 planks | H64: 4 | I64: 200 goods traded | L64: This is today's pack horse, now behind an extension.
A65: Trade | B65: Trade Center | C65: Upgrade | D65: Trading post | E65: Space for 2 more workers, twice storing room | G65: 6 stone, 10 timber | H65: 8 | I65: 600 goods traded
A66: Trade | B66: Huge ships | C66: Upgrade | D66: Docks | E66: Doubles export per worker | F66: 12 timber, 6 wood parts a year | G66: 12 timber, 20 planks, 6 wood parts | H66: 13 | I66: 1000 goods traded | L66: Upkeep 12 timber and 6 wood parts a month is far above anything else; a year? (5 Questions)
A67: Civic
A68: Civic | B68: Expanded draught stable | C68: Upgrade | D68: Draught stable | E68: Same size, double the room (6) | G68: 4 timber, 6 planks | H68: 8 | I68: the stable full (3 animals)
A69: Civic | B69: Mounted guard | C69: Extension | D69: Courthouse | E69: Allows buying horses for the courthouse to increase capacity | F69: grain for the horses | G69: 6 planks, 4 stone | H69: 8 | I69: the courthouse at full crew
A70: Civic | B70: Improved granary | C70: Upgrade | D70: Granary | E70: Double store room and increase worker capacity by 2 | G70: 6 stone, 6 planks | H70: 6 | I70: 300 food stored | L70: Second step of the store chain after the Loft.
A71: Civic | B71: Improved warehouse | C71: Upgrade | D71: Storehouse | E71: Double store room and increase worker capacity by 2 | G71: 6 stone, 6 planks | H71: 6 | I71: 300 materials stored | L71: Second step of the store chain after the Loft.
A72: Civic | B72: Ox-carts | C72: Extension | D72: Storehouse / Granary | E72: An ox from a draught stable: haulers carry twice as much and go half as far again. | F72: an ox (stall) | G72: 4 planks, 2 wood parts | H72: 4 | I72: an improved store and a free stall | L72: Your "carrying capacity by X": I set it to twice the load. An extension rather than an upgrade, since it adds an ox.
A73: Looks | B73: Heraldic banners | C73: Town option | D73: Manor | E73: Banners in the lord's arms on the manor, towers and market: +prestige; cloth and dyes once. | F73: cloth, dyes (once) | H73: 2 | J73: Uses the arms editor in the town itself. | L73: Kept (your answer).
A74: Knowledge for all of step 4 | H74: =SUM(H5:H73) | L74: Range now includes the trade and civic rows you added.
A75: Knowledge earned in the Borough and City (0 Stages) | H75: ='0 Stages'!H8+'0 Stages'!H9
A76: Left after steps 1-3 and 4 | H76: ='0 Stages'!H5+'0 Stages'!H6+'0 Stages'!H7+'0 Stages'!H8+'0 Stages'!H9-'1 Budget check'!D10-H74
A78: Left for step 7 (the shape of the learning panel) and for charters to interact with. Choices are counted once even though only one side is taken.
A80: Price multiplier for step 4 (your lever: late unlocks should take many years) | H80: 4
A81: Step 4 at that price | H81: =H74*H80
A82: Left after steps 1-4 at that price, by the end of the City | H82: ='0 Stages'!H5+'0 Stages'!H6+'0 Stages'!H7+'0 Stages'!H8+'0 Stages'!H9-'1 Budget check'!D10-H81
A83: Share of all knowledge the game offers that steps 1-4 then take | H83: =('1 Budget check'!D10+H81)/('0 Stages'!H5+'0 Stages'!H6+'0 Stages'!H7+'0 Stages'!H8+'0 Stages'!H9)
A84: Steps 1-3 stay at their prices (they hold the essentials). The rest of the gap is for big City projects (step 7).

Sheet 2 Questions
A1: Step 2: decisions
A2: My recommendation first; yours in the yellow column.
A4: # | B4: Question | C4: My recommendation | D4: Your answer
A5: 1 | B5: Boots move up from the Townhouse to the Merchant's House. | C5: Yes. It makes the Townhouse fit its knowledge budget, and leather was the Townhouse's third new line anyway (G17). | D5: I think they should be both garment needs and either is enough to Townhouse, while merchant needs both
A6: 2 | B6: The Merchant's House is built with mortar and glass instead of planks and tools. | C6: Yes: mortar and glass get the use they lack, and the stone town looks the part. | D6: Yes
A7: 3 | B7: A fifth home level, the Patrician House, for the City. | C7: Yes, but small: it gives the City a home to grow into and stained glass and fine clothes a steady demand. | D7: Coments on the appropriate section
A8: 4 | B8: A Bathhouse as a Merchant's House need. | C8: Yes: a service the well-to-do want, and a civic use for fuel. If not, the stone church alone. | D8: Yes
A9: 5 | B9: Tax Office: 40 villagers each, 1 paper a month; tally sticks or no paper, half. | C9: Yes to start; the other feeds (wax tablets, parchment) only if a line needs a new use. | D9: Changed unlock, was only in city
A10: 6 | B10: The Trading Post is free from the start. | C10: Yes: the Hamlet needs to buy tools and sell surplus before there are taxes. | D10: yes
A11: 7 | B11: Does a fountain (decoration) also count as water for homes? | C11: Yes, a little closer reach than a well: a reason to build pretty water in the town centre. | D11: Much closer reach
A12: 8 | B12: Public School or Sunday School? | C12: Both, as you described: the school is a building, the Sunday school a church extension (step 4). A town picks one or both. | D12: Both
A13: 9 | B13: The manor becomes required for taxes. Should its first level be cheaper? | C13: Yes: 40 timber, 15 planks, 20 coins, so a Hamlet can afford it in its first year. | D13: Yes

Sheet 2 Questions (round 2)
A1: Step 2, round 2: what your edits left open
A2: My reading first; correct it in the yellow column.
A4: # | B4: Question | C4: My reading / recommendation | D4: Your answer
A5: 1 | B5: Scale everything by four (G19), not only construction? | C5: Yes. Dividing only the costs makes building four times cheaper next to what the town makes and earns; doing everything keeps the proportions and the smaller numbers. | D5: Just reduce production speed of most goods. Food production remain untouched/wating for step 8
A6: 2 | B6: Fine pottery: a Merchant's House need, or one of its luxuries? Your edits list it in both, and the goods sheet now calls it a luxury. | C6: A luxury only. The Merchant's House then needs clothes, boots and medicine, plus one luxury. | D6: agreed
A7: 3 | B7: Books and mead are no longer luxuries (your goods edits). Glassware joins. Is the list now jewellery, fine clothes, glassware, wine and fine pottery? | C7: Yes. Books go to the monastery, university and scriptorium; mead stays a tavern drink. | D7: yes
A8: 4 | B8: Garments: clothes or boots meets the Townhouse; the Merchant's House needs both. | C8: Agreed: I mark the clothes line as the Townhouse essential (cheaper) and boots as the Merchant's. | D8: Ok
A9: 5 | B9: The Bathhouse is City-gated, but the Merchant's House (Borough) needs it. | C9: Move it to the Patrician House's needs, or open it at Borough. I'd open it at Borough. | D9: Open at borough
A10: 6 | B10: The Builder's Yard is "linked to draught stables": it needs a draught stable built (an exception to G7, like the Cooper)? | C10: Yes, as a condition: it is useless without an ox. | D10: Yes
A11: 7 | B11: Market and Alehouse serve homes by workers (your notes); the market's workers by space, one per stall per 2 squares. | C11: Yes (G20). An alehouse tapster serves about eight homes. | D11: yes, may have to change, since I don't want residents scaling so much with house level, thus the city will have more houses
A12: 8 | B12: The Courthouse: past Borough, unhappiness grows faster than the population unless homes are covered by policing. | C12: A happiness penalty growing with population above 90, removed for homes a courthouse covers (by its crew). Numbers in step 8. | D12: Ok
A13: 9 | B13: One church per town (the wooden church and its rebuilds). | C13: Yes; the cathedral stays separate and also serves as a church. | D13: Yes
A14: 10 | B14: The Armoury becomes a manor building for prestige and looks; arms go. | C14: Noted for step 5. The retinue then needs another cost (coins and prestige). | D14: Ok
A15: 11 | B15: Potter: clay + fuel + dye. | C15: Yes: glazes coloured with dye; gives dyes a third use. | D15: Yes

Sheet 3 Questions
A1: Step 3: decisions
A2: My recommendation first; yours in the yellow column.
A4: # | B4: Question | C4: My recommendation | D4: Your answer
A5: 1 | B5: Fine clothes from an Embroiderer, stained glass from a Glazier: two new buildings. | C5: Yes: each is the end of a line, and both take dyes, which gives the dye line its weight. | D5: Agreed
A6: 2 | B6: Parchment: a tanner recipe (hides) that feeds offices and books like paper does. | C6: Yes: the option you wanted for administrative buildings, without a new building; hides get a second use. | D6: Agreed
A7: 3 | B7: Mead opens to every town (honey from the beekeeper); the Meadmakers charter doubles honey and mead instead. | C7: Yes: the beekeeper otherwise only makes food. | D7: Agreed
A8: 4 | B8: Clothes and boots: the courthouse watch wears them (its running cost), a second use for both. | C8: Yes: it also makes policing cost something real. | D8: Agreed
A9: 5 | B9: Medicine: sickness events can be stopped by spending medicine. | C9: Yes: there is already a sickness event; it becomes the second use. | D9: Ok, but let's watch it closely
A10: 6 | B10: The jeweller sets silver with glass. | C10: Yes: glass becomes a jeweller's input and silver keeps its one use. | D10: Agreed
A11: 7 | B11: Silver stays bought or from the Deep Veins charter: no silver mine. | C11: Yes for now: one less raw line (G17). A silver vein could be a later map feature. | D11: Agreed, jeweller inevitably comes after jeweler anyway
A12: 8 | B12: Books stay a charter craft (scriptorium) or bought; monasteries and the university read them. | C12: Yes, as you said. A monastery could copy its own books as an extension (step 4). | D12: Agreed, but monasteries will only consume
A13: 9 | B13: Fine pottery and jewellery have one use (luxury), which G14 allows with export. | C13: Keep: luxuries are their own reward. | D13: Agreed

Sheet 4 Questions
A1: Step 4: decisions
A2: My recommendation first; yours in the yellow column.
A4: # | B4: Question | C4: My recommendation | D4: Your answer
A5: 1 | B5: One extension per workplace, or more as the town grows? | C5: One. It keeps each workplace a clear decision and the art readable. | D5: Answered
A6: 2 | B6: Upgrades: one per kind of workplace? | C6: Yes. More levels would turn back into flat bonuses. | D6: For now it is one, but we may add a longer chain
A7: 3 | B7: Choices are town-wide and final. | C7: Yes, final; it is what makes them choices. A charter could allow one change later (step 6). | D7: Yes
A8: 4 | B8: Iron plough overlaps the Heavy Plough charter. | C8: Keep both: the charter then gives more (e.g. no tool upkeep on the plough). Decided in step 6. | D8: Yes
A9: 5 | B9: Town options (limewash, dyed tunics, roofs, banners): worth the art? | C9: Yes, they are the cheapest way to make towns look different from one another, and each gives an existing good a running use. | D9: Cool
A10: 6 | B10: Too many entries? 37 here. | C10: Build them in waves: one upgrade or extension per line first, choices and options after the playthrough. | D10: I added more :)

Sheet 5 Manor
A1: Step 5: the manor and the lord's buildings
A2: Costs from 2 Costs where they exist; new ones on the same scale. Every manor building must touch the manor or a manor decoration that touches it (your note).
A4: Building | B4: Kind | C4: What it does | D4: Gate | E4: Knowledge | F4: Cost | G4: Workers | H4: Runs on | I4: Limit | J4: Prestige a month | K4: Change from today | L4: Your notes | M4: My notes
A5: The seat
A6: Manor Hall | B6: Seat | C6: The lord's timber hall. Taxes begin with it (up to 45 villagers); feasts are held here; houses the lord's household. | D6: Hamlet | F6: 10 timber, 6 planks, 6 stone | G6: 0 | H6: — | I6: one | J6: 0 | K6: Required for taxes now; cheaper.
A7: Manor House | B7: Enlarge | C7: More storage and prestige; festivals. | D7: Village | F7: 4 timber, 10 planks, 10 stone, 12 coins | G7: 0 | H7: — | J7: 1.5
A8: Stone Manor | B8: Enlarge | C8: More prestige; opens walls, watch towers, the manor garden and the armoury. | D8: Town | F8: 5 stone, 10 dressed stone, 10 tiles, 40 coins | G8: 0 | H8: — | J8: 3
A9: Palace | B9: Enlarge | C9: A palace for the lord: the most prestige; opens the atelier, the tiltyard and the barracks. | D9: Borough | F9: 10 dressed stone, 6 mortar, 4 tools, 60 coins | G9: 0 | H9: — | J9: 4.5 | K9: New fourth level (a palace rather than a fortified manor: your answer).
A10: On the grounds
A11: Lord's Stable | B11: Building | C11: The lord rides out, faster; a groom. Let toggle horse | D11: Village | F11: 10 timber, 5 planks, 30 coins | G11: 1 | H11: — | I11: one | J11: 0.5 | K11: Was open from the start. | M11: A toggle in the lord's panel: ride or walk.
A12: Armoury | B12: Building | C12: Fits out the guard: the retinue and watchmen wear armour (looks); needed to raise the retinue. | D12: Town | F12: 6 planks, 6 stone, 2 tools, 20 coins | G12: 1 | H12: 1 tool a year | I12: one | J12: 1 | K12: Moves from industry; arms are gone (your note).
A13: Manor Garden | B13: Building | C13: Formal gardens: prestige and beauty. | D13: Stone Manor | F13: 8 planks, 15 stone, 6 dressed stone, 200 coins | G13: 0 | H13: — | I13: one | J13: 4
A14: Patrons' Atelier | B14: Building | C14: Consumes a lot of goods, but every month has a chance of generating a lot of prestige and a great art. Chance start at 0 and goes up 1% every month it is maintained consecutively. When fired, enters a 1 year cooldow and start over with 50% of the previous chance) failing to maintain resets cooldown | D14: Palace | E14: 8 | F14: 6 dressed stone, 8 glass | G14: 2 | H14: 1 dye, 2 luxury, 10 gp, 1 dressed stone, 1 paper a month | I14: one | K14: New (yours). Replaces the dovecote; works of art now come from here. | M14: How I read it: each month fully supplied adds 1% to the chance of a masterpiece (one of the works of art in 5 Lordship, plus a burst of prestige). After one, a year's rest, then it starts again from half the chance it had. A month unsupplied puts the chance back to 0.
A15: Stew pond (proposal) | B15: Building | C15: A fish pond on the grounds: fish for the lord's table, a little prestige. | D15: Manor House | E15: 4 | F15: 4 stone, 2 planks | G15: 1 | H15: — | I15: one | J15: 0.5 | K15: New.
A16: Deer park (proposal) | B16: Zone | C16: A fenced wood on the grounds: venison and prestige; the Royal Hunt charter hunts here. | D16: Stone Manor | E16: 6 | F16: fence: 12 timber, must be 12 tiles | G16: 1 | H16: — | I16: one | J16: 1 | K16: New. | M16: Fence: 12 timber, and at least 12 tiles (yours).
A17: Tiltyard (proposal) | B17: Building | C17: Lists for jousting: fairs bring twice the prestige. | D17: Palace | E17: 8 | F17: 8 planks, 4 stone, 40 coins | G17: 0 | H17: — | I17: one | J17: 1 | K17: New.
A18: Defence
A19: Watch Tower | B19: Building | C19: A watchman: +2 happiness, warns of wolves and bandits. | D19: Stone Manor | F19: 3 planks, 10 stone, 6 tiles | G19: 1 | H19: 2 food a month | I19: 2 for each rank above Village | J19: 0.5 | K19: Limit (your note).
A20: Town wall (section) | B20: Building | C20: Rings the town: safe behind 40 sections; a postern every sixth. | D20: Stone Manor | F20: 6 stone | G20: 0 | H20: — | J20: 1 per 20 sections (max 6) | K20: Exempt from touching the manor (5 Questions).
A21: Barracks | B21: Building | C21: Raises the retinue (60 prestige, 25 coins; 3 coins a month), and its men help the courthouse: it polices more homes. | D21: Palace | E21: 6 | F21: 8 stone, 4 dressed stone, 2 tools | G21: 1 | H21: 2 food a month | J21: 1 | K21: New (yours); replaces the gatehouse. The retinue is raised here. | M21: The retinue: men-at-arms who guard the roads when wolves or bandits come (the two events that bring trouble), +2 happiness.
A23: The manor's grounds: the manor, its buildings and the manor decorations (hedges, flower beds, gardens) touching them form one estate; the grass under it blends into a single dirt shape (art, your note).

Sheet 5 Lordship
A1: Step 5: feasts, fairs, titles, the retinue and works of art
A2: Today's numbers from the game, my proposal beside them. Coin costs follow the cheaper scale of construction.
A4: What | B4: When | C4: Costs today | D4: Proposed cost | E4: Gives | F4: Change | G4: Your notes | H4: My notes
A5: Feasts and festivals
A6: Harvest feast | B6: Each autumn, at the manor | C6: A meal for every villager, a cask for every eight | D6: Same | E6: +14 happiness for half a year, +10 prestige (with drink) | F6: Any tavern drink counts (step 3). | G6: ok
A7: May Day | B7: Spring, Manor House | C7: Food for a quarter of the villagers | D7: Same | E7: +6 happiness for a season, +3 prestige | G7: ok
A8: Midsummer | B8: Summer, Manor House | C8: Food for a quarter, 20 timber (a bonfire) | D8: Food for a quarter, 10 firewood | E8: +6 happiness, +3 prestige | F8: Timber down to the new scale; firewood for a bonfire. | G8: ok
A9: The great fair | B9: Once a year, from Town | C9: 400 coins, half again each fair | D9: 100 coins, half again each fair | E9: 15 prestige (+5 each fair), +8 happiness | F9: Coins on the new scale; the tiltyard doubles the prestige. | G9: ok
A10: The lord
A11: Baron | B11: Town | C11: 500 prestige | D11: Same | E11: Taxes a tenth more | F11: Prestige income is unchanged, so titles stay. | G11: Ididn't get. Do you have to buy the titles? | H11: Yes: titles are bought with prestige once the town is big enough, each with a lasting boon. Your Marquess took the old Duke's numbers; Duke gets new ones.
A12: Earl | B12: Borough | C12: 1500 prestige | D12: Same | E12: +3 happiness
A13: Marquess | B13: City | C13: — | D13: 3000 prestige | E13: Merchants buy half as much again | F13: New title between Earl and Duke (yours).
A14: Duke | B14: City, with a Palace | C14: 4000 prestige | D14: 6000 prestige | E14: Prestige a fifth more every month | F14: Now the last title. | H14: The retinue row moved to the Barracks (5 Manor).
A15: Works of art
A16: Great tapestry | B16: An artist | C16: — | D16: A masterpiece from the atelier (chance) | E16: +3 happiness for good | F16: Was bought with prestige and goods; now made by an artist. | G16: new
A17: Stained-glass windows | B17: An artist | C17: — | D17: A masterpiece from the atelier (chance) | E17: +3 happiness for good | F17: Fewer panes for the glazier's slower pace. | G17: new
A18: Renowed statue | B18: An artist | C18: — | D18: A masterpiece from the atelier (chance) | E18: +2 Prestige per month | G18: new
A19: Literature Classic | B19: An artist | C19: — | D19: A masterpiece from the atelier (chance) | E19: +1 Prestige per month +1 knowledge per month | G19: new
A20: Alchemical treatise | B20: An artist | C20: — | D20: A masterpiece from the atelier (chance) | E20: +2 knowledge/month | G20: new

Sheet 5 Great Works
A1: Step 5: the Great Works
A2: One of each per town. Costs as you set them in 2 Costs.
A4: Work | B4: Gate | C4: Cost | D4: Workers | E4: Gives today | F4: Proposed | G4: Counts for the Patrician House? | H4: Your notes | I4: My notes
A5: Statue | B5: Town | C5: 5 dressed stone, 1 tool, 50 coins | D5: 0 | E5: +1 prestige a month, beauty | F5: Same: the small monument. | G5: No
A6: Covered Market Hall | B6: Town | C6: 6 planks, 20 dressed stone, 30 tiles, 50 coins | D6: 10 | E6: Ten stalls under one roof | F6: Same; stalls by crew (G20). | G6: Yes
A7: Bell Tower | B7: Borough | C7: 5 planks, 30 stone, 10 dressed stone, 100 coins | D7: 0 | E7: +2 prestige a month | F7: Also: all work 2% faster (your answer). | G7: Yes | H7: Raids? no such thing | I7: There are two trouble events today, wolves and bandits; with the watch-tower role gone, the bell tower only speeds work.
A8: Cathedral | B8: Borough | C8: 45 dressed stone, 15 mortar, 8 stained glass, 6 tools, 250 coins | D8: 2 | E8: Serves as a church far and wide, +6 happiness, +3 prestige, +3 knowledge | F8: Same; its windows commission now needs stained glass. | G8: Yes | H8: Ok
A9: University | B9: Borough | C9: 30 planks, 20 dressed stone, 30 tiles, 10 books, 150 coins | D9: 3 | E9: 8 knowledge and prestige while fed two books a month; +5% to every workplace | F9: Knowledge by crew (G20). Its 10 a month is most of the late surplus (5 Questions). | G9: Yes
A10: Guildhall | B10: City | C10: 25 dressed stone, 40 tiles, 12 mortar, 6 stained glass, 400 coins | D10: 2 | E10: +4 prestige, exports fetch a fifth more | F10: Also: each charter costs a fifth less. | G10: Yes | H10: ok
A11: Connection to the Royal Road | B11: Borough | C11: Buildable double square wide stone road that must connect two opposite sides of the map (bridges count tripe). | D11: 0 | F11: movement along the royal road is 30% faster then in coblestone. Import factor reduced by 0.15 and export increase by 0.15 | G11: No | H11: New | I11: Bridges triple the cost per tile. Built in one go along a path you draw from edge to edge? Or tile by tile until it connects? I'd do tile by tile, and the bonus starts once it links two opposite edges.

Sheet 5 Questions
A1: Step 5: decisions (and what step 4 left open)
A2: My recommendation first; yours in the yellow column.
A4: # | B4: Question | C4: My recommendation | D4: Your answer
A5: 1 | B5: A fourth manor level, the Fortified Manor, at Borough? | C5: Yes: the manor otherwise stops growing at Town, while the town goes on to Borough and City. | D5: Ok! But maybe we can make a palace intead of fortified manor, since we already have fortification around it
A6: 2 | B6: Town walls exempt from touching the manor? | C6: Yes: they ring the town. Watch towers and the gatehouse too, since they stand on the wall. | D6: Ok
A7: 3 | B7: New manor buildings: dovecote, stew pond, deer park, tiltyard, gatehouse. Which? | C7: All five are small; if fewer, keep the tiltyard and the deer park (they tie into fairs and the Royal Hunt). | D7: Refer to page
A8: 4 | B8: Retinue without arms: 60 prestige, 25 coins and an armoury; 3 coins a month. | C8: Yes. | D8: Retinue without arms? Where is it from?
A9: 5 | B9: Fairs at 100 coins (half again each time) instead of 400. | C9: Yes, to match the cheaper coin costs. | D9: ok
A10: 6 | B10: Works of art need goods: the tapestry cloth and dyes, the windows 6 stained glass. | C10: Yes: prestige plus the showpiece goods. | D10: Reworked
A11: 7 | B11: Which Great Works count for the Patrician House? | C11: Any but the statue, anywhere in town. | D11: Reworked
A12: 8 | B12: Bell tower and guildhall get a second effect (festivals and warnings; cheaper charters). | C12: Yes: every Great Work should change something, not just add prestige. | D12: Belltower increase general efficiency by 2%
A13: 9 | B13: Pears are learned in step 1 (with plums) and again here as a variant. | C13: Pears move to step 4 with their slow, rich trait; plums stay in step 1. | D13: ok
A14: 10 | B14: Strawberries: a new good, or berries? | C14: Berries: no new good (G17). | D14: I thought of new good
A15: 11 | B15: Holstein and Wagyu are modern names. | C15: Frisian (milk) and Highland (beef). | D15: sounds good
A16: 12 | B16: Toll navigation and Trade deals have the same text. | C16: Toll navigation for docks, Trade deals for trading posts: the same bonus where each applies. | D16: No, it is the same effect and apply to all trade
... A19: 15 | B19: Late knowledge: the Borough and City earn about 2,200; everything so far costs about 400. | C19: Lower the late sources (university 5, Merchant's House 0.15) and add a few big City projects to spend on; settle in step 7. | D19: I guess we should scale down from before or inflate no essential costs of later (by a lot, a player should have to play a lot of years to complete them all)

Sheet 6 Charters
A1: Step 6: the charters, reworked for the new economy
A2: Each path: two ranks, then a choice of two. Today's charter beside my proposal; "Status" says what changes and why.
A4: Path | B4: Rank | C4: Today | D4: Today it does | E4: Status | F4: Proposed | G4: Proposed effect | H4: Opens | I4: Your notes | J4: My notes
A5: Metalwork | C5: Path drawback | D5: Smoke from the forges: homes a little less happy.
A6: Metalwork | B6: 1 | C6: Master Smiths | D6: Bloomeries, blacksmiths and armouries a quarter faster. | E6: Rework | F6: Master Smiths | G6: Bloomeries and blacksmiths a quarter faster. | I6: When is silver revealed? Maybe it should reveal 2-4 spots here
A7: Metalwork | B7: 2 | C7: Deep Veins | D7: Bog iron never runs out; now and then silver comes up with it. | E7: Keep | F7: Deep Veins | G7: Reveals 2 to 4 silver veins on the map, worked by a Silver Mine. | H7: Silver Mine | J7: Today silver only comes now and then with bog iron. Your note: reveal spots instead. They need a building to work them, so the charter opens one.
A8: Metalwork | B8: 3a | C8: Jewellers' Guild | D8: Opens the jeweller; jewellers twice as fast; prestige for each. | E8: Keep | F8: Jewellers' Guild | G8: As today. | H8: Jeweller's Shop
A9: Metalwork | B9: 3b | C9: Armourers' Guild | D9: Armouries make half again; arms fetch half again. | E9: Replace | F9: Ironmongers' Guild | G9: Blacksmiths a third faster, every workplace wears a fifth fewer tools, and tools fetch half again. | I9: fetching 1.5 sounds enough
A10: Orchard Masters | C10: Path drawback | D10: Orchard keepers need a third more hands.
A11: Orchard Masters | B11: 1 | C11: Grafting | D11: Orchards and hives 30% more. | E11: Keep | F11: Grafting | G11: As today.
A12: Orchard Masters | B12: 2 | C12: Vines and Nurseries | D12: Vines for grapes; trees bear sooner. | E12: Keep | F12: Vines and Nurseries | G12: As today. | H12: Vines
A13: Orchard Masters | B13: 3a | C13: Vintners | D13: Opens the winery; wine and cider half again and dearer. | E13: Keep | F13: Vintners | G13: As today. | H13: Winery
A14: Orchard Masters | B14: 3b | C14: Meadmakers | D14: Hives twice the honey; mead from the brewhouse; honey cakes +4 happiness. | E14: Rework | F14: Meadmakers | G14: Beekeepers and hives twice the honey, mead half again; honey cakes +4 happiness. (Mead is open to all since step 3.)
A15: Erudition | C15: Path drawback | D15: Scholars shun the fields: farms yield a little less.
A16: Erudition | B16: 1 | C16: Scribes | D16: Opens the scriptorium; half again books; +1 prestige. | E16: Keep | F16: Scribes | G16: As today; books from paper or parchment. | H16: Scriptorium
A17: Erudition | B17: 2 | C17: Guild Schools | D17: Workshops 10% faster. | E17: Keep | F17: Guild Schools | G17: As today.
A18: Erudition | B18: 3a | C18: University Charter | D18: University reads one book; 10% learning instead of 5%; +2 prestige. | E18: Rework | F18: University Charter | G18: University reads one book a month and teaches half again (knowledge); learning 10% instead of 5%.
A19: Erudition | B19: 3b | C19: Cathedral School | D19: +6 happiness, +2 prestige, books dearer. | E19: Rework | F19: Cathedral School | G19: +6 happiness, +2 prestige; the cathedral and churches teach twice as much.
A20: Harmony with Nature | C20: Path drawback | D20: Quarries and mines a fifth slower.
A21: Harmony with Nature | B21: 1 | C21: Woodland Lore | D21: Foragers and hunters 50% more. | E21: Keep | F21: Woodland Lore | G21: Foragers and hunters half again.
A22: Harmony with Nature | B22: 2 | C22: Greenwood | D22: Forests regrow twice as fast; woodcutters a fifth more; +3 happiness. | E22: Keep | F22: Greenwood | G22: As today.
A23: Harmony with Nature | B23: 3a | C23: Druids' Grove | D23: +6 happiness; herbs; +1 prestige. | E23: Keep | F23: Druids' Grove | G23: +6 happiness, herbs, +1 prestige; and homes may go up a level, or keep theirs, with one need unmet. | I23: Contact with nature keeps citziens happy, hosing requirements for upkeep and upgrade allows one condition not met | J23: Your note: contact with nature keeps the people content.
A24: Harmony with Nature | B24: 3b | C24: Royal Hunt | D24: Hunters half again; a prestige for each hunting camp. | E24: Rework | F24: Royal Hunt | G24: Hunters half again; two more herds of deer roam the map; the deer park yields twice and brings 2 more prestige. | I24: Appear 2 extra heard of dear in the map | J24: Deer herds as wildlife that hunters can follow (art: like the bear and turtles).
A25: Traders | C25: Path drawback | D25: Taxes are less popular.
A26: Traders | B26: 1 | C26: Market Charter | D26: Buy 15% cheaper, sell 20% dearer. | E26: Keep | F26: Market Charter | G26: As today (stacks with the trade upgrades of step 4).
A27: Traders | B27: 2 | C27: Fair Town | D27: Merchants buy twice as much. | E27: Keep | F27: Fair Town | G27: As today.
A28: Traders | B28: 3a | C28: Merchant Guild | D28: Exports 30% more. | E28: Keep | F28: Merchant Guild | G28: As today.
A29: Traders | B29: 3b | C29: Toll Roads | D29: A coin a month for every two tiles of stone road or cobbles. | E29: Rework | F29: Toll Roads | G29: As today, and the Royal Road pays three times as much per tile.
A30: Farmers | C30: Path drawback | D30: Pastures carry a fifth fewer animals.
A31: Farmers | B31: 1 | C31: Three-Field Rotation | D31: Harvests 20% larger. | E31: Keep | F31: Three-Field Rotation | G31: As today.
A32: Farmers | B32: 2 | C32: Heavy Plough | D32: Farmers tend half as many fields again. | E32: Rework | F32: Heavy Plough | G32: The iron plough (step 4) costs no knowledge and wears no tools; farmers tend a quarter more besides.
A33: Farmers | B33: 3a | C33: Breadbasket | D33: Granaries twice; mills and bakeries 30% more. | E33: Keep | F33: Breadbasket | G33: As today.
A34: Farmers | B34: 3b | C34: Brewers' Guild | D34: Ale half again; ale fetches double. | E34: Keep | F34: Brewers' Guild | G34: Every brewhouse drink half again; drinks fetch half again. | I34: Fetches 1.5 is enough
A35: Shepherds | C35: Path drawback | D35: Fields yield a tenth less.
A36: Shepherds | B36: 1 | C36: Good Husbandry | D36: Herds 30% more. | E36: Keep | F36: Good Husbandry | G36: As today.
A37: Shepherds | B37: 2 | C37: Great Herds | D37: Pastures carry half again. | E37: Keep | F37: Great Herds | G37: As today (stacks with animal sheds).
A38: Shepherds | B38: 3a | C38: Butchers' Guild | D38: Slaughter half again meat; tanners a third faster. | E38: Keep | F38: Butchers' Guild | G38: As today; parchment too.
A39: Shepherds | B39: 3b | C39: Fine Cheese | D39: Cheese half again and double the price. | E39: Keep | F39: Fine Cheese | G39: Cheese half again; cheese fetches half again. | I39: 1.5 times
A40: Artisans' Guilds (new) | C40: Path drawback | D40: The dye works stink: homes near a dyer a little less happy.
A41: Artisans' Guilds (new) | B41: 1 | C41: — | E41: New | F41: Dyers' Guild | G41: Dyers half again; berries dye as well as woad.
A42: Artisans' Guilds (new) | B42: 2 | C42: — | E42: New | F42: Glaziers | G42: Glassworks and glaziers a third faster.
A43: Artisans' Guilds (new) | B43: 3a | C43: — | E43: New | F43: Drapers' Guild | G43: Embroiderers twice as fast; fine clothes fetch a quarter more. | H43: Tapestry looms (the atelier's tapestry twice as likely) | I43: 1.25 is enough
A44: Artisans' Guilds (new) | B44: 3b | C44: — | E44: New | F44: Potters' Guild | G44: Potters twice as fast; fine pottery counts as two luxuries for a home.
A46: Cost: prestige, 40 for the first and 1.6 times more for each one after (unchanged). A town can take a little of several paths or go deep in one; each third rank is one of two.

Sheet 6 Charter costs
A1: Charter prices: rising so that about two full paths fit in a game
A2: Price of the n-th charter = base x growth^(n-1). Blue cells are levers. Two full paths = 6 charters (three ranks each).
A4: Base price (first charter) | B4: 40
A5: Growth for each charter after | B5: 1.8
A6: Prestige a typical game can put into charters | B6: 2500 | C6: Estimate: what a game earns after titles; recheck in step 8 against the real prestige income.
A8: Charter | B8: Price | C8: Total so far | D8: Affordable?
A9: 1 | B9: =ROUND($B$4*$B$5^(A9-1),0) | C9: =SUM($B$9:B9) | D9: =IF(C9<=$B$6,"Yes","No")
A10: 2 | B10: =ROUND($B$4*$B$5^(A10-1),0) | C10: =SUM($B$9:B10) | D10: =IF(C10<=$B$6,"Yes","No")
A11: 3 | B11: =ROUND($B$4*$B$5^(A11-1),0) | C11: =SUM($B$9:B11) | D11: =IF(C11<=$B$6,"Yes","No")
A12: 4 | B12: =ROUND($B$4*$B$5^(A12-1),0) | C12: =SUM($B$9:B12) | D12: =IF(C12<=$B$6,"Yes","No")
A13: 5 | B13: =ROUND($B$4*$B$5^(A13-1),0) | C13: =SUM($B$9:B13) | D13: =IF(C13<=$B$6,"Yes","No")
A14: 6 | B14: =ROUND($B$4*$B$5^(A14-1),0) | C14: =SUM($B$9:B14) | D14: =IF(C14<=$B$6,"Yes","No")
A15: 7 | B15: =ROUND($B$4*$B$5^(A15-1),0) | C15: =SUM($B$9:B15) | D15: =IF(C15<=$B$6,"Yes","No")
A16: 8 | B16: =ROUND($B$4*$B$5^(A16-1),0) | C16: =SUM($B$9:B16) | D16: =IF(C16<=$B$6,"Yes","No")
A17: 9 | B17: =ROUND($B$4*$B$5^(A17-1),0) | C17: =SUM($B$9:B17) | D17: =IF(C17<=$B$6,"Yes","No")
A18: 10 | B18: =ROUND($B$4*$B$5^(A18-1),0) | C18: =SUM($B$9:B18) | D18: =IF(C18<=$B$6,"Yes","No")
A20: Charters a typical game affords | B20: =COUNTIF(D9:D18,"Yes")
A21: Today: base 40, growth 1.6 (the 6th costs 420, all six 1,450).

Sheet 6 Questions
A1: Step 6: decisions
A2: My recommendation first; yours in the yellow column.
A4: # | B4: Question | C4: My recommendation | D4: Your answer
A5: 1 | B5: An eighth path, Artisans' Guilds (dyes, glass, fine clothes, pottery)? | C5: Yes: steps 1-3 built a whole luxury industry that no path speaks to. | D5: Sounds cool
A6: 2 | B6: Armourers' Guild becomes the Ironmongers' Guild (arms are gone). | C6: Yes: tools are the late game's bottleneck, so a tool path matters. | D6: Ok
A7: 3 | B7: Heavy Plough now empowers the iron plough extension instead of duplicating it. | C7: Yes. | D7: Ok
A8: 4 | B8: Charters only open at Town; should the third rank also wait for Borough? | C8: Yes: today a town can rush a whole path at Town; the choice at the end should come later. | D8: I think we should make price rise exponentially. A regular player should unlock 2 full paths in a game
A9: 5 | B9: Charter cost stays prestige (40, then 1.6 times more each). | C9: Yes for now; recheck in step 8 against the new prestige income. | D9: Agree with rechecking
A10: 6 | B10: Should a charter let you re-pick one town choice (step 4)? | C10: No: choices stay final; charters stay about specialising. | D10: No
A11: 7 | B11: Every path keeps a drawback. | C11: Yes: it is what makes going deep a real decision. | D11: Yes

Sheet 7 Learning panel
A1: Step 7: the learning panel
A2: How unlocks are shown and bought. Not a strict tree: a web of cards grouped by craft, with arrows only where one thing really needs another.
A4: ID | B4: Part | C4: How it works | D4: Why | E4: Your call | F4: Your notes
A5: Layout
A6: L1 | B6: Opening it | C6: A book button beside the knowledge counter in the top bar opens a full-screen panel (like the big trading-post window). Locked cards in the build menu open it at their own card. | D6: One place to learn; the build menu points to it. | E6: Agreed
A7: L2 | B7: Tabs by craft | C7: Timber & stone · Farming & food · Herds & orchards · Cloth & dyes · Metal & glass · Civic & learning · Trade & roads · City projects. | D7: Crafts read as stories (timber to planks to the water sawmill); categories like "Industry" would mix unrelated lines. | E7: Changes | F7: I think civic, learning, trade & roads could be together.
A8: L3 | B8: Columns by depth | C8: Within a tab, cards run left to right: basic buildings, then mixed goods, then upgrades, extensions, variants and choices. | D8: The eye moves from "how to start" to "how to refine". | E8: No | F8: I want them to look like scout patches on a wooden board, scattered with the appropriate ones together
A9: L4 | B9: Arrows | C9: Only where something needs another: an upgrade or extension needs its building, a chain step needs the step before, a condition names a good. Everything else floats free. | D9: A web, not a tree: you said it need not be a tree exactly. | E9: Agreed
A10: Cards
A11: L5 | B11: A card | C11: Picture (the building icon), name, kind (building, upgrade, extension, variant, choice, option), what it changes in one line, knowledge price. | E11: Agreed
A12: L6 | B12: States | C12: Hidden until its inputs can be had (made or bought) · Locked: shows what it waits for (rank, knowledge, condition with a progress bar) · Ready to learn · Learned. | D12: Players see the next steps, not 150 cards at once. | E12: No hidden, only locks and further
A13: L7 | B13: Choices | C13: Shown as two (or three) cards joined by "or". Picking one greys the others for good, with a confirm that says so. | D13: Choices are final (step 4). | E13: Agreed
A14: L8 | B14: Learning | C14: Click a ready card, confirm, knowledge is spent; the card turns gold and the build menu gains it. Fingamoboblius comments on the first few. | E14: Ok, let's see how it looks
A15: Guidance
A16: L9 | B16: What next | C16: A "Suggested" strip at the top: what the next home level needs that is not learned yet, cheapest first. | D16: Nobody stalls on a house level (G9). | E16: Players are not stupid, an explanation by Finga will sufice
A17: L10 | B17: Old saves | C17: Saves from before the rework start with everything they have already built learned (and nothing else). | D17: You said saves may break; this keeps them loading. | E17: If it is easy, ok

Sheet 7 City projects
A1: Step 7: City projects, big learning for the late game
A2: Knowledge sinks with a lasting effect each, bought in the learning panel. Prices in blue; the total is checked against what is left.
A4: Project | B4: What it changes | C4: Knowledge | D4: Also costs | E4: Needs | F4: Why | G4: Your notes
A5: The Great Survey | B5: Every deposit on the map is shown (ore, clay, sand, silver if veins exist) and the soil map is drawn for fields. | C5: 80 | D5: 4 paper | E5: a Tax Office | F5: Planning the late town.
A6: Master Builders | B6: Every building site rises a fifth faster. | C6: 120 | D6: 4 books | E6: a Mason's Lodge
A7: Agricultural Treatise | B7: Fields and orchards a tenth more. | C7: 120 | D7: 4 books | E7: Beans learned
A8: Hydraulic Engineering | B8: Every building beside water (mills, sawmill, bellows, paper mill) a fifth faster. | C8: 150 | D8: 4 books, 6 tools | E8: two water buildings | F8: Rewards a river town.
A9: Codified Law | B9: Courthouses police half as many homes again; the late-Borough unhappiness grows slower. | C9: 150 | D9: 6 paper | E9: a Courthouse
A10: Navigation Charts | B10: Docks and the Royal Road trade a tenth better. | C10: 150 | D10: 4 books | E10: a Dock or the Royal Road
A11: School of Medicine | B11: Sickness events can always be stopped with medicine; homes use medicine a third slower. | C11: 150 | D11: 6 books | E11: an Infirmary
A12: Learned Treatise (repeatable) | B12: Each one written brings 25 prestige and +1 happiness for a year. | C12: 60 | D12: 2 books | E12: — | F12: An endless sink once everything is learned.
A14: City projects (once each, the treatise once) | C14: =SUM(C5:C12)
A15: Left by the end of the City after steps 1-4 (4 Depth) | C15: ='4 Depth'!H82
A16: Left after the projects (spent on treatises) | C16: =C15-C14
A18: Projects need no rank (G6), but their price and the buildings they need keep them late.

Sheet 7 Questions
A1: Step 7: decisions
A2: My recommendation first; yours in the yellow column.
A4: # | B4: Question | C4: My recommendation | D4: Your answer
A5: 1 | B5: Tabs by craft (timber & stone, farming & food...) rather than by build-menu category or by kind? | C5: By craft: it reads like the production lines you designed in steps 1-4. | D5: Talked about, though if there is too few in each page can merge in extraction and maybe growing or something and the misc we discussed
A6: 2 | B6: Cards hidden until their inputs can be had? | C6: Yes, with a counter "12 more to discover" per tab so nothing feels missing. | D6: No
A7: 3 | B7: A "Suggested" strip for what the next home level needs. | C7: Yes. | D7: No
A8: 4 | B8: City projects as the late sink, with one repeatable treatise. | C8: Yes; the list is a first pass, add or cut freely. | D8: No, let's rebalance knowledge gain/cost so a player only completes all techs a few years after city. As an easy solution for now: all current knowledge gain is divided by 8, gain 1 knowledge or 2 when reaching city (or 1 village, 1 city)
A9: 5 | B9: Silver Mine: Deep Veins only, or could the Great Survey also reveal one vein for any town? | C9: Deep Veins only: it keeps the charter special. | D9: No GP
A10: 6 | B10: Deer herds (Royal Hunt): wildlife like the bear, that hunters follow? | C10: Yes: a hunter near a herd catches more. | D10: Don't hunters already have to go where the wildlife is to hunt?
A11: 7 | B11: After this, step 8: the final tuning. Shall I start building the rework branch in parallel, from the decisions so far? | C11: Yes: the data (unlock table, costs, upkeep, recipes) can go in while you look at the numbers, and the balance pass runs on the real game. | D11: Go ahead and build, balance, test, design everything new. When you are happy with it, merge with main. Then review drawings, work on the remade tutorial and add in everypage a a small symbol to call Fingamaboblineus to explain the panel over.

Sheet Questions
A1: Decisions before building
A2: My recommendation is first; write yours in the yellow column.
A4: # | B4: Question | C4: My recommendation | D4: Your answer
A5: 1 | B5: Is knowledge spent on each unlock (like prestige), or a running total that opens things as it passes thresholds? | C5: Spent. Thresholds would open everything in the same order every game; spending makes each unlock a choice. | D5: Spent on each unlock
A6: 2 | B6: Starting set as in G10? | C6: Yes. Forester, sawmill and fields follow within the first year for a few knowledge. | D6: What is G10?
A7: 3 | B7: Upkeep rule G15: woodcutters, quarries and farms wear wood parts instead of tools until the Town. | C7: Yes: today they wear tools nothing in a Village can make. | D7: Responded in others
A8: 4 | B8: The wooden church moves to Village rank, and Timber Houses give a little knowledge (0 Knowledge). | C8: Yes: otherwise a Village earns almost no knowledge. Final call in step 2 (civic). | D8: Yes
A9: 5 | B9: A new 'Elders' lore' trickle from the camp and manor hall (0.5 a month). | C9: Yes: the Hamlet needs something to learn with. | D9: Good
A10: 6 | B10: The bloomery burns charcoal instead of firewood. | C10: Yes: historically right, and charcoal gets a second use beside glass. | D10: We will always use fuel, charcoal will just be more efficient
A11: 7 | B11: Drop oats (no source, no use). | C11: Yes. | D11: Yes
A12: 8 | B12: Conditions count everything a town has ever produced, kept as a running tally per good (also good for a stats screen). | C12: Yes. | D12: Yes, but modifyied uses as said
A13: 9 | B13: How should unlocks be shown before the tree exists? | C13: A "Learning" panel listing what can be learned now, its cost and condition; locked cards in the build menu show what they wait for. | D13: I think it has to be a full panel, with one screen for each category of construction (food/civil/industry/...) or some other division we see fit (construction/choices/ extensions/... Or woodwork/metalwork/farming/...)
